<?xml version="1.0" encoding="utf-8"?>
<Return xmlns="http://www.irs.gov/efile" xmlns:xsi="http://www.w3.org/2001/XMLSchema-instance" xsi:schemaLocation="http://www.irs.gov/efile" returnVersion="2009v1.4">
  <ReturnHeader binaryAttachmentCount="0">
    <Timestamp>2010-09-02T10:13:47-05:00</Timestamp>
    <TaxPeriodEndDate>2010-06-30</TaxPeriodEndDate>
    <PreparerFirm>
      <PreparerFirmBusinessName>
        <BusinessNameLine1>Grabel Schnieders Hollman &amp; Co CPA</BusinessNameLine1>
      </PreparerFirmBusinessName>
      <PreparerFirmUSAddress>
        <AddressLine1>206 W Argonne Ste 200</AddressLine1>
        <City>Kirkwood</City>
        <State>MO</State>
        <ZIPCode>63122</ZIPCode>
      </PreparerFirmUSAddress>
    </PreparerFirm>
    <ReturnType>990EZ</ReturnType>
    <TaxPeriodBeginDate>2009-07-01</TaxPeriodBeginDate>
    <Filer>
      <EIN>436048852</EIN>
      <Name>
        <BusinessNameLine1>INTERNATIONAL UNION OF PAINTER &amp; ALLIED</BusinessNameLine1>
        <BusinessNameLine2>TRADES UNION LOCAL #1199</BusinessNameLine2>
      </Name>
      <NameControl>INTE</NameControl>
      <Phone>3146472453</Phone>
      <USAddress>
        <AddressLine1>2501 59TH STREET</AddressLine1>
        <City>ST LOUIS</City>
        <State>MO</State>
        <ZIPCode>63110</ZIPCode>
      </USAddress>
    </Filer>
    <Officer>
      <Name>DUANE OEHMEN</Name>
      <Title>TREASURER</Title>
      <Phone>3146472453</Phone>
      <DateSigned>2010-08-31</DateSigned>
      <AuthorizeThirdParty>1</AuthorizeThirdParty>
    </Officer>
    <Preparer>
      <Name>Grabel Schnieders Hollman Co CPA</Name>
      <Phone>3144347310</Phone>
      <DatePrepared>2010-08-23</DatePrepared>
    </Preparer>
    <TaxYear>2009</TaxYear>
    <BuildTS>2016-02-24 21:20:13Z</BuildTS>
  </ReturnHeader>
  <ReturnData documentCount="2">
    <IRS990EZ documentId="RetDoc1234200001" referenceDocumentId="RetDoc10045800000">
      <MethodOfAccountingCash>X</MethodOfAccountingCash>
      <ScheduleBNotRequired>X</ScheduleBNotRequired>
      <WebSite>N/A</WebSite>
      <Organization501c typeOf501cOrganization="5">X</Organization501c>
      <GrossReceipts>123448</GrossReceipts>
      <MembershipDues>121848</MembershipDues>
      <InvestmentIncome>1600</InvestmentIncome>
      <TotalRevenue>123448</TotalRevenue>
      <BenefitsPaidToOrForMembers>1200</BenefitsPaidToOrForMembers>
      <SalariesOtherCompEmplBenefits>22616</SalariesOtherCompEmplBenefits>
      <FeesAndOthPymtToIndContractors>1262</FeesAndOthPymtToIndContractors>
      <OccupancyRentUtilitiesAndMaint>3300</OccupancyRentUtilitiesAndMaint>
      <PrintingPublicationsPostage>2021</PrintingPublicationsPostage>
      <OtherExpensesTotal referenceDocumentId="RetDoc2020500001">99277</OtherExpensesTotal>
      <TotalExpenses>129676</TotalExpenses>
      <ExcessOrDeficitForYear>-6228</ExcessOrDeficitForYear>
      <NetAssetsOrFundBalancesBOY>100873</NetAssetsOrFundBalancesBOY>
      <NetAssetsOrFundBalancesEOY>94645</NetAssetsOrFundBalancesEOY>
      <CashSavingsAndInvestments>
        <BOY>101786</BOY>
        <EOY>95604</EOY>
      </CashSavingsAndInvestments>
      <TotalAssets>
        <BOY>101786</BOY>
        <EOY>95604</EOY>
      </TotalAssets>
      <SumOfTotalLiabilities referenceDocumentId="RetDoc2022900001">
        <BOY>913</BOY>
        <EOY>959</EOY>
      </SumOfTotalLiabilities>
      <NetAssetsOrFundBalances>
        <BOY>100873</BOY>
        <EOY>94645</EOY>
      </NetAssetsOrFundBalances>
      <PrimaryExemptPurpose>TO REPRESENT LOCAL MEMBERS IN UNION ACTIVITIES</PrimaryExemptPurpose>
      <ProgramServiceAccomplishment>
        <DescriptionProgramServiceAccom>TO REPRESENT LOCAL MEMBERS IN UNION ACTIVITIES</DescriptionProgramServiceAccom>
        <GrantsAndAllocations>0</GrantsAndAllocations>
        <ProgramServiceExpenses>0</ProgramServiceExpenses>
      </ProgramServiceAccomplishment>
      <OfficerDirectorTrusteeKeyEmpl>
        <PersonName>RICH O'NEAL</PersonName>
        <AddressUS>
          <AddressLine1>2501 59TH STREET</AddressLine1>
          <City>ST LOUIS</City>
          <State>MO</State>
          <ZIPCode>63110</ZIPCode>
        </AddressUS>
        <Title>RECORDING SECRETARY</Title>
        <AvgHoursPerWkDevotedToPosition>1.80</AvgHoursPerWkDevotedToPosition>
        <Compensation>3080</Compensation>
        <ContriToEmplBenefitPlansEtc>0</ContriToEmplBenefitPlansEtc>
        <ExpenseAccountOtherAllowances>0</ExpenseAccountOtherAllowances>
      </OfficerDirectorTrusteeKeyEmpl>
      <OfficerDirectorTrusteeKeyEmpl>
        <PersonName>DUANE OEHMEN</PersonName>
        <AddressUS>
          <AddressLine1>2501 59TH STREET</AddressLine1>
          <City>ST LOUIS</City>
          <State>MO</State>
          <ZIPCode>63110</ZIPCode>
        </AddressUS>
        <Title>TREASURER/DELEGATE</Title>
        <AvgHoursPerWkDevotedToPosition>1.80</AvgHoursPerWkDevotedToPosition>
        <Compensation>3651</Compensation>
        <ContriToEmplBenefitPlansEtc>0</ContriToEmplBenefitPlansEtc>
        <ExpenseAccountOtherAllowances>0</ExpenseAccountOtherAllowances>
      </OfficerDirectorTrusteeKeyEmpl>
      <OfficerDirectorTrusteeKeyEmpl>
        <PersonName>CHRIS ROBINSON</PersonName>
        <AddressUS>
          <AddressLine1>2501 59TH STREET</AddressLine1>
          <City>ST LOUIS</City>
          <State>MO</State>
          <ZIPCode>63110</ZIPCode>
        </AddressUS>
        <Title>PRESIDENT/DELEGATE</Title>
        <AvgHoursPerWkDevotedToPosition>1.00</AvgHoursPerWkDevotedToPosition>
        <Compensation>456</Compensation>
        <ContriToEmplBenefitPlansEtc>0</ContriToEmplBenefitPlansEtc>
        <ExpenseAccountOtherAllowances>0</ExpenseAccountOtherAllowances>
      </OfficerDirectorTrusteeKeyEmpl>
      <OfficerDirectorTrusteeKeyEmpl>
        <PersonName>DENNIS BUECHTER</PersonName>
        <AddressUS>
          <AddressLine1>2501 59TH STREET</AddressLine1>
          <City>ST LOUIS</City>
          <State>MO</State>
          <ZIPCode>63110</ZIPCode>
        </AddressUS>
        <Title>PRESIDENT/DELEGATE</Title>
        <AvgHoursPerWkDevotedToPosition>0.50</AvgHoursPerWkDevotedToPosition>
        <Compensation>2111</Compensation>
        <ContriToEmplBenefitPlansEtc>0</ContriToEmplBenefitPlansEtc>
        <ExpenseAccountOtherAllowances>0</ExpenseAccountOtherAllowances>
      </OfficerDirectorTrusteeKeyEmpl>
      <OfficerDirectorTrusteeKeyEmpl>
        <PersonName>COZETTA MCKILLOP</PersonName>
        <AddressUS>
          <AddressLine1>2501 59TH STREET</AddressLine1>
          <City>ST LOUIS</City>
          <State>MO</State>
          <ZIPCode>63110</ZIPCode>
        </AddressUS>
        <Title>WARDEN</Title>
        <AvgHoursPerWkDevotedToPosition>0.40</AvgHoursPerWkDevotedToPosition>
        <Compensation>685</Compensation>
        <ContriToEmplBenefitPlansEtc>0</ContriToEmplBenefitPlansEtc>
        <ExpenseAccountOtherAllowances>0</ExpenseAccountOtherAllowances>
      </OfficerDirectorTrusteeKeyEmpl>
      <OfficerDirectorTrusteeKeyEmpl>
        <PersonName>MARIO PUCCI</PersonName>
        <AddressUS>
          <AddressLine1>2501 59TH STREET</AddressLine1>
          <City>ST LOUIS</City>
          <State>MO</State>
          <ZIPCode>63110</ZIPCode>
        </AddressUS>
        <Title>FINANCIAL SECRETARY</Title>
        <AvgHoursPerWkDevotedToPosition>6.00</AvgHoursPerWkDevotedToPosition>
        <Compensation>10609</Compensation>
        <ContriToEmplBenefitPlansEtc>0</ContriToEmplBenefitPlansEtc>
        <ExpenseAccountOtherAllowances>0</ExpenseAccountOtherAllowances>
      </OfficerDirectorTrusteeKeyEmpl>
      <OfficerDirectorTrusteeKeyEmpl>
        <PersonName>VINCE ZANTI</PersonName>
        <AddressUS>
          <AddressLine1>2501 59TH STREET</AddressLine1>
          <City>ST LOUIS</City>
          <State>MO</State>
          <ZIPCode>63110</ZIPCode>
        </AddressUS>
        <Title>VICE PRESIDENT</Title>
        <AvgHoursPerWkDevotedToPosition>0.50</AvgHoursPerWkDevotedToPosition>
        <Compensation>656</Compensation>
        <ContriToEmplBenefitPlansEtc>0</ContriToEmplBenefitPlansEtc>
        <ExpenseAccountOtherAllowances>0</ExpenseAccountOtherAllowances>
      </OfficerDirectorTrusteeKeyEmpl>
      <OfficerDirectorTrusteeKeyEmpl>
        <PersonName>BOB LATIMORE</PersonName>
        <AddressUS>
          <AddressLine1>2501 59TH STREET</AddressLine1>
          <City>ST LOUIS</City>
          <State>MO</State>
          <ZIPCode>63110</ZIPCode>
        </AddressUS>
        <Title>TRUSTEE</Title>
        <AvgHoursPerWkDevotedToPosition>0.20</AvgHoursPerWkDevotedToPosition>
        <Compensation>57</Compensation>
        <ContriToEmplBenefitPlansEtc>0</ContriToEmplBenefitPlansEtc>
        <ExpenseAccountOtherAllowances>0</ExpenseAccountOtherAllowances>
      </OfficerDirectorTrusteeKeyEmpl>
      <OfficerDirectorTrusteeKeyEmpl>
        <PersonName>JOSEPH BARRETT</PersonName>
        <AddressUS>
          <AddressLine1>2501 59TH STREET</AddressLine1>
          <City>ST LOUIS</City>
          <State>MO</State>
          <ZIPCode>63110</ZIPCode>
        </AddressUS>
        <Title>TRUSTEE</Title>
        <AvgHoursPerWkDevotedToPosition>0.20</AvgHoursPerWkDevotedToPosition>
        <Compensation>57</Compensation>
        <ContriToEmplBenefitPlansEtc>0</ContriToEmplBenefitPlansEtc>
        <ExpenseAccountOtherAllowances>0</ExpenseAccountOtherAllowances>
      </OfficerDirectorTrusteeKeyEmpl>
      <OfficerDirectorTrusteeKeyEmpl>
        <PersonName>SHAWN OSTER</PersonName>
        <AddressUS>
          <AddressLine1>2501 59TH STREET</AddressLine1>
          <City>ST LOUIS</City>
          <State>MO</State>
          <ZIPCode>63110</ZIPCode>
        </AddressUS>
        <Title>TRUSTEE</Title>
        <AvgHoursPerWkDevotedToPosition>0.20</AvgHoursPerWkDevotedToPosition>
        <Compensation>570</Compensation>
        <ContriToEmplBenefitPlansEtc>0</ContriToEmplBenefitPlansEtc>
        <ExpenseAccountOtherAllowances>0</ExpenseAccountOtherAllowances>
      </OfficerDirectorTrusteeKeyEmpl>
      <OfficerDirectorTrusteeKeyEmpl>
        <PersonName>JOHN KENNAMANN</PersonName>
        <AddressUS>
          <AddressLine1>2501 59TH STREET</AddressLine1>
          <City>ST LOUIS</City>
          <State>MO</State>
          <ZIPCode>63110</ZIPCode>
        </AddressUS>
        <Title>TRUSTEE</Title>
        <AvgHoursPerWkDevotedToPosition>0.20</AvgHoursPerWkDevotedToPosition>
        <Compensation>456</Compensation>
        <ContriToEmplBenefitPlansEtc>0</ContriToEmplBenefitPlansEtc>
        <ExpenseAccountOtherAllowances>0</ExpenseAccountOtherAllowances>
      </OfficerDirectorTrusteeKeyEmpl>
      <OfficerDirectorTrusteeKeyEmpl>
        <PersonName>SCOTT WANDZEL</PersonName>
        <AddressUS>
          <AddressLine1>2501 59TH STREET</AddressLine1>
          <City>ST LOUIS</City>
          <State>MO</State>
          <ZIPCode>63110</ZIPCode>
        </AddressUS>
        <Title>TRUSTEE</Title>
        <AvgHoursPerWkDevotedToPosition>0.20</AvgHoursPerWkDevotedToPosition>
        <Compensation>228</Compensation>
        <ContriToEmplBenefitPlansEtc>0</ContriToEmplBenefitPlansEtc>
        <ExpenseAccountOtherAllowances>0</ExpenseAccountOtherAllowances>
      </OfficerDirectorTrusteeKeyEmpl>
      <ActivitiesNotPreviouslyRpt>0</ActivitiesNotPreviouslyRpt>
      <MadeChangesToOrgnzngEtcDoc>0</MadeChangesToOrgnzngEtcDoc>
      <OrganizationHadUBI>0</OrganizationHadUBI>
      <OrganizationDissolvedEtc>0</OrganizationDissolvedEtc>
      <DirectIndirectPoliticalExpend>0</DirectIndirectPoliticalExpend>
      <MadeLoansToFromOfficers>0</MadeLoansToFromOfficers>
      <ProhibitedTaxShelterTrans>0</ProhibitedTaxShelterTrans>
      <TheBooksAreInCareOf>
        <NameBusiness>
          <BusinessNameLine1>DUANE OEHMEN</BusinessNameLine1>
        </NameBusiness>
        <AddressUS>
          <AddressLine1>2501 59TH STREET</AddressLine1>
          <City>ST LOUIS</City>
          <State>MO</State>
          <ZIPCode>63110</ZIPCode>
        </AddressUS>
        <TelephoneNumber>3146472453</TelephoneNumber>
      </TheBooksAreInCareOf>
      <ForeignFinancialAccount>0</ForeignFinancialAccount>
      <ForeignOffice>0</ForeignOffice>
      <MaintainAnyDonorAdvisedFunds>0</MaintainAnyDonorAdvisedFunds>
      <RelatedOrgControlledEntity>0</RelatedOrgControlledEntity>
    </IRS990EZ>
    <TransferPrsnlBnftContractsDecl documentId="RetDoc10045800000">
      <Declaration>The organization did not, during the year, receive any funds, directly,or indirectly, to pay premiums on a personal benefit contract.The organization, did not, during the year, pay any premiums, directly,or indirectly, on a personal benefit contract.</Declaration>
    </TransferPrsnlBnftContractsDecl>
  </ReturnData>
</Return>