<?xml version="1.0" encoding="utf-8"?>
<Return xmlns="http://www.irs.gov/efile" xmlns:xsi="http://www.w3.org/2001/XMLSchema-instance" xsi:schemaLocation="http://www.irs.gov/efile" returnVersion="2009v1.4">
  <ReturnHeader binaryAttachmentCount="0">
    <Timestamp>2011-01-25T09:22:19-06:00</Timestamp>
    <TaxPeriodEndDate>2010-06-30</TaxPeriodEndDate>
    <PreparerFirm>
      <PreparerFirmBusinessName>
        <BusinessNameLine1>LBA Certified Public Accountants PA</BusinessNameLine1>
      </PreparerFirmBusinessName>
      <PreparerFirmUSAddress>
        <AddressLine1>501 RIVERSIDE AVENUE SUITE 800</AddressLine1>
        <City>JACKSONVILLE</City>
        <State>FL</State>
        <ZIPCode>322024939</ZIPCode>
      </PreparerFirmUSAddress>
    </PreparerFirm>
    <ReturnType>990</ReturnType>
    <TaxPeriodBeginDate>2009-07-01</TaxPeriodBeginDate>
    <Filer>
      <EIN>593580979</EIN>
      <Name>
        <BusinessNameLine1>Florida Endowment Foundation for</BusinessNameLine1>
        <BusinessNameLine2>Florida's Graduates Inc</BusinessNameLine2>
      </Name>
      <NameControl>FLOR</NameControl>
      <Phone>3864395730</Phone>
      <USAddress>
        <AddressLine1>306 South Oceanshore Blvd No a1a</AddressLine1>
        <City>Flagler Beach</City>
        <State>FL</State>
        <ZIPCode>32136</ZIPCode>
      </USAddress>
    </Filer>
    <Officer>
      <Name>HEATHER M BEAVEN</Name>
      <Title>CEO</Title>
      <Phone>3864395730</Phone>
      <DateSigned>2011-01-12</DateSigned>
      <AuthorizeThirdParty>1</AuthorizeThirdParty>
    </Officer>
    <Preparer>
      <Phone>9043964015</Phone>
    </Preparer>
    <TaxYear>2009</TaxYear>
    <BuildTS>2016-02-24 21:20:13Z</BuildTS>
  </ReturnHeader>
  <ReturnData documentCount="5">
    <IRS990 documentId="RetDoc1038000001" referenceDocumentId="RetDoc1044400001">
      <NameOfPrincipalOfficerPerson>HEATHER M BEAVEN</NameOfPrincipalOfficerPerson>
      <AddressPrincipalOfficerUS>
        <AddressLine1>306 South Oceanshore Blvd No a1a</AddressLine1>
        <City>Flagler Beach</City>
        <State>FL</State>
        <ZIPCode>32136</ZIPCode>
      </AddressPrincipalOfficerUS>
      <GrossReceipts>1115563</GrossReceipts>
      <GroupReturnForAffiliates>0</GroupReturnForAffiliates>
      <Organization501c typeOf501cOrganization="3">X</Organization501c>
      <WebSite>WWW.FLGRADUATES.ORG</WebSite>
      <TypeOfOrganizationCorporation>X</TypeOfOrganizationCorporation>
      <YearFormation>1998</YearFormation>
      <StateLegalDomicile>FL</StateLegalDomicile>
      <ActivityOrMissionDescription>THE ORGANIZATION WAS ESTABLISHED TO CREATE A STATEWIDE ORGANIZATION FOCUSED ON PROVIDING EDUCATION, WORKFORCE DEVELOPMENT, AND ECONOMIC DEVELOPMENT FOR FLORIDA STUDENTS.</ActivityOrMissionDescription>
      <NbrVotingMembersGoverningBody>28</NbrVotingMembersGoverningBody>
      <NbrIndependentVotingMembers>28</NbrIndependentVotingMembers>
      <TotalNbrEmployees>26</TotalNbrEmployees>
      <TotalNbrVolunteers>35</TotalNbrVolunteers>
      <TotalGrossUBI>0</TotalGrossUBI>
      <NetUnrelatedBusinessTxblIncome>0</NetUnrelatedBusinessTxblIncome>
      <ContributionsGrantsPriorYear>1776553</ContributionsGrantsPriorYear>
      <ContributionsGrantsCurrentYear>1053235</ContributionsGrantsCurrentYear>
      <ProgramServiceRevenueCY>57380</ProgramServiceRevenueCY>
      <InvestmentIncomePriorYear>3222</InvestmentIncomePriorYear>
      <InvestmentIncomeCurrentYear>770</InvestmentIncomeCurrentYear>
      <OtherRevenuePriorYear>1747</OtherRevenuePriorYear>
      <OtherRevenueCurrentYear>4178</OtherRevenueCurrentYear>
      <TotalRevenuePriorYear>1781522</TotalRevenuePriorYear>
      <TotalRevenueCurrentYear>1115563</TotalRevenueCurrentYear>
      <GrantsAndSimilarAmntsCY>0</GrantsAndSimilarAmntsCY>
      <BenefitsPaidToMembersCY>0</BenefitsPaidToMembersCY>
      <SalariesEtcPriorYear>1095311</SalariesEtcPriorYear>
      <SalariesEtcCurrentYear>973173</SalariesEtcCurrentYear>
      <TotalProfFundrsngExpCY>0</TotalProfFundrsngExpCY>
      <TotalFundrsngExpCurrentYear>16431</TotalFundrsngExpCurrentYear>
      <OtherExpensePriorYear>439401</OtherExpensePriorYear>
      <OtherExpensesCurrentYear>309224</OtherExpensesCurrentYear>
      <TotalExpensesPriorYear>1534712</TotalExpensesPriorYear>
      <TotalExpensesCurrentYear>1282397</TotalExpensesCurrentYear>
      <RevenuesLessExpensesPriorYear>246810</RevenuesLessExpensesPriorYear>
      <RevenuesLessExpensesCY>-166834</RevenuesLessExpensesCY>
      <TotalAssetsBOY>390625</TotalAssetsBOY>
      <TotalAssetsEOY>268156</TotalAssetsEOY>
      <TotalLiabilitiesBOY>25904</TotalLiabilitiesBOY>
      <TotalLiabilitiesEOY>70269</TotalLiabilitiesEOY>
      <NetAssetsOrFundBalancesBOY>364721</NetAssetsOrFundBalancesBOY>
      <NetAssetsOrFundBalancesEOY>197887</NetAssetsOrFundBalancesEOY>
      <MissionDescription>THE ORGANIZATION'S MISSION IS TO BRING ACADEMIC, WORK, LIFE AND ECONOMIC OPPORTUNITIES TO STUDENTS WHOSE POTENTIAL TO CONTRIBUTE TO A ROBUST FLORIDA IS LARGELY UNTAPPED.</MissionDescription>
      <SignificantNewProgramServices>0</SignificantNewProgramServices>
      <SignificantChange>0</SignificantChange>
      <Expense>1086545</Expense>
      <Revenue>61558</Revenue>
      <Description>The Foundation is currently made up of four programs that operate both independently and cooperatively, depending on the needs of external partners carrying out the Foundation's mission.Jobs for Florida's Graduates ("JFG") is the main program of the Foundation. JFG is a competency based work and life skills program for Florida students that is delivered by licensed educators for middle schools, high schools, community colleges, juvenile justice facilities and community based organizations. This program is affiliated with the National Jobs for America's Graduates, which operates in 28 states.Girls Get IT! ("GGIT") was created to develop a statewide network that offers young women opportunities to connect and explore Science, Technology, Engineering, and Math ("STEM") and Information Technology ("IT") leading to rewarding careers. GGIT was created by The Florida Distance Learning Consortium and Cisco Systems, Inc. in 2005. GGIT works with middle and high schools to increase female student participation and graduation rates in STEM and IT coursework, provide STEM and IT career exploration opportunities, and ultimately increase the number of women employed in the STEM and IT fields across the state of Florida.Victory Over Instability by Choosing Education ("VOICE") is a multi-media youth center concept designed to give young people real-world, work-based learning opportunities in journalism, poetry, song-writing, composing, graphic design, and publishing. The VOICE center, located in Palatka, Florida, offers both JFG and GGIT programs.The SUPERB initiative focuses on social responsibility, teamwork skills, diversity appreciation and common bonds across cultures, expanding friendships and support systems, crisis/bullying prevention and intervention, personal expression, and self-awareness. SUPERB uses career exploration, work based learning and community service as a tool of conceptual relevance. SUPERB was created by Senator Jeremy Ring and Nova Southeastern University Graduate School of Humanities and Social Sciences. The Foundation assumed operations of SUPERB in January 2009.</Description>
      <TotalProgramServiceExpense>1086545</TotalProgramServiceExpense>
      <DescribedIn501C3 referenceDocumentId="RetDoc1039100001">1</DescribedIn501C3>
      <ScheduleBRequired referenceDocumentId="RetDoc1234500001">1</ScheduleBRequired>
      <PoliticalActivities>0</PoliticalActivities>
      <LobbyingActivities>0</LobbyingActivities>
      <DonorAdvisedFunds referenceDocumentId="RetDoc1040000001">0</DonorAdvisedFunds>
      <ConservationEasements referenceDocumentId="RetDoc1040000001">0</ConservationEasements>
      <CollectionsOfArt referenceDocumentId="RetDoc1040000001">0</CollectionsOfArt>
      <CreditCounseling referenceDocumentId="RetDoc1040000001">0</CreditCounseling>
      <TermOrPermanentEndowments referenceDocumentId="RetDoc1040000001">0</TermOrPermanentEndowments>
      <BalanceSheetAmountsReported referenceDocumentId="RetDoc1040000001">1</BalanceSheetAmountsReported>
      <IndependentAuditFinancialStmt referenceDocumentId="RetDoc1040000001">1</IndependentAuditFinancialStmt>
      <ConsolidatedAuditFinancialStmt referenceDocumentId="RetDoc1040000001">0</ConsolidatedAuditFinancialStmt>
      <School>0</School>
      <ForeignOffice>0</ForeignOffice>
      <ForeignActivities>0</ForeignActivities>
      <MoreThan5000KToOrganizations>0</MoreThan5000KToOrganizations>
      <MoreThan5000KToIndividuals>0</MoreThan5000KToIndividuals>
      <ProfessionalFundraising>0</ProfessionalFundraising>
      <FundraisingActivities>0</FundraisingActivities>
      <Gaming>0</Gaming>
      <Hospital>0</Hospital>
      <GrantsToOrganizations>0</GrantsToOrganizations>
      <GrantsToIndividuals>0</GrantsToIndividuals>
      <ScheduleJRequired>0</ScheduleJRequired>
      <TaxExemptBonds>0</TaxExemptBonds>
      <ExcessBenefitTransaction>0</ExcessBenefitTransaction>
      <PriorExcessBenefitTransaction>0</PriorExcessBenefitTransaction>
      <LoanToOfficerOrDQP>0</LoanToOfficerOrDQP>
      <GrantToRelatedPerson>0</GrantToRelatedPerson>
      <BsnssRltnshpWithOrganization>0</BsnssRltnshpWithOrganization>
      <BsnssRltnshpThruFamilyMember>0</BsnssRltnshpThruFamilyMember>
      <OfficerEntityWithBsnssRltnshp>0</OfficerEntityWithBsnssRltnshp>
      <DeductibleNonCashContributions>0</DeductibleNonCashContributions>
      <DeductibleContributionsOfArt>0</DeductibleContributionsOfArt>
      <Terminated>0</Terminated>
      <PartialLiquidation>0</PartialLiquidation>
      <DisregardedEntity>0</DisregardedEntity>
      <RelatedEntity>0</RelatedEntity>
      <RelatedOrgControlledEntity>0</RelatedOrgControlledEntity>
      <TransfersToExemptNonChrtblOrg>0</TransfersToExemptNonChrtblOrg>
      <ActivitiesConductedPartnership>0</ActivitiesConductedPartnership>
      <ScheduleORequired>1</ScheduleORequired>
      <NumberFormsTransmittedWith1096>2</NumberFormsTransmittedWith1096>
      <NumberW2GIncluded>0</NumberW2GIncluded>
      <ComplianceWithBackupWitholding>1</ComplianceWithBackupWitholding>
      <NumberOfEmployees>26</NumberOfEmployees>
      <EmploymentTaxReturnsFiled>1</EmploymentTaxReturnsFiled>
      <UnrelatedBusinessIncome>0</UnrelatedBusinessIncome>
      <ForeignFinancialAccount>0</ForeignFinancialAccount>
      <ProhibitedTaxShelterTrans>0</ProhibitedTaxShelterTrans>
      <TaxablePartyNotification>0</TaxablePartyNotification>
      <NonDeductibleContributions>0</NonDeductibleContributions>
      <QuidProQuoContributions>0</QuidProQuoContributions>
      <Form8282PropertyDisposedOf>0</Form8282PropertyDisposedOf>
      <ExcessBusinessHoldings>0</ExcessBusinessHoldings>
      <TaxableDistributions>0</TaxableDistributions>
      <DistributionToDonor>0</DistributionToDonor>
      <NbrVotingGoverningBodyMembers>28</NbrVotingGoverningBodyMembers>
      <NumberIndependentVotingMembers>28</NumberIndependentVotingMembers>
      <FamilyOrBusinessRelationship>0</FamilyOrBusinessRelationship>
      <DelegationOfManagementDuties>0</DelegationOfManagementDuties>
      <ChangesToOrganizingDocs>0</ChangesToOrganizingDocs>
      <MaterialDiversionOrMisuse>0</MaterialDiversionOrMisuse>
      <MembersOrStockholders>0</MembersOrStockholders>
      <ElectionOfBoardMembers>0</ElectionOfBoardMembers>
      <DecisionsSubjectToApproval>0</DecisionsSubjectToApproval>
      <MinutesOfGoverningBody>1</MinutesOfGoverningBody>
      <MinutesOfCommittees>1</MinutesOfCommittees>
      <OfficerMailingAddress>0</OfficerMailingAddress>
      <LocalChapters>0</LocalChapters>
      <Form990ProvidedToGoverningBody>1</Form990ProvidedToGoverningBody>
      <ConflictOfInterestPolicy>1</ConflictOfInterestPolicy>
      <AnnualDisclosureCoveredPersons>0</AnnualDisclosureCoveredPersons>
      <RegularMonitoringEnforcement>1</RegularMonitoringEnforcement>
      <WhistleblowerPolicy>1</WhistleblowerPolicy>
      <DocumentRetentionPolicy>1</DocumentRetentionPolicy>
      <CompensationProcessCEO>1</CompensationProcessCEO>
      <CompensationProcessOther>1</CompensationProcessOther>
      <InvestmentInJointVenture>0</InvestmentInJointVenture>
      <StatesWhereCopyOfReturnIsFiled>FL</StatesWhereCopyOfReturnIsFiled>
      <UponRequest>X</UponRequest>
      <TheBooksAreInCareOf>
        <NameBusiness>
          <BusinessNameLine1>HEATHER BEAVEN</BusinessNameLine1>
        </NameBusiness>
        <TelephoneNumber>3864395730</TelephoneNumber>
        <AddressUS>
          <AddressLine1>306 SOUTH OCEANSHORE BLVD</AddressLine1>
          <City>FLAGLER BEACH</City>
          <State>FL</State>
          <ZIPCode>32136</ZIPCode>
        </AddressUS>
      </TheBooksAreInCareOf>
      <Form990PartVIISectionA>
        <NamePerson>Shannon Hewett</NamePerson>
        <Title>Chairwoman</Title>
        <AverageHoursPerWeek>0.50</AverageHoursPerWeek>
        <IndividualTrusteeOrDirector>X</IndividualTrusteeOrDirector>
        <Officer>X</Officer>
        <ReportableCompFromOrganization>0</ReportableCompFromOrganization>
        <ReportableCompFromRelatedOrgs>0</ReportableCompFromRelatedOrgs>
        <OtherCompensation>0</OtherCompensation>
      </Form990PartVIISectionA>
      <Form990PartVIISectionA>
        <NamePerson>Senator Gary Siplin</NamePerson>
        <Title>Co-Vice Chairman, Ex-Off</Title>
        <AverageHoursPerWeek>0.50</AverageHoursPerWeek>
        <IndividualTrusteeOrDirector>X</IndividualTrusteeOrDirector>
        <Officer>X</Officer>
        <ReportableCompFromOrganization>0</ReportableCompFromOrganization>
        <ReportableCompFromRelatedOrgs>0</ReportableCompFromRelatedOrgs>
        <OtherCompensation>0</OtherCompensation>
      </Form990PartVIISectionA>
      <Form990PartVIISectionA>
        <NamePerson>Rep Will Weatherford</NamePerson>
        <Title>co-Vice Chairman, Ex-Off</Title>
        <AverageHoursPerWeek>0.50</AverageHoursPerWeek>
        <IndividualTrusteeOrDirector>X</IndividualTrusteeOrDirector>
        <Officer>X</Officer>
        <ReportableCompFromOrganization>0</ReportableCompFromOrganization>
        <ReportableCompFromRelatedOrgs>0</ReportableCompFromRelatedOrgs>
        <OtherCompensation>0</OtherCompensation>
      </Form990PartVIISectionA>
      <Form990PartVIISectionA>
        <NamePerson>Lois Gracey</NamePerson>
        <Title>Treasurer &amp; Finance/Audi</Title>
        <AverageHoursPerWeek>0.50</AverageHoursPerWeek>
        <IndividualTrusteeOrDirector>X</IndividualTrusteeOrDirector>
        <Officer>X</Officer>
        <ReportableCompFromOrganization>0</ReportableCompFromOrganization>
        <ReportableCompFromRelatedOrgs>0</ReportableCompFromRelatedOrgs>
        <OtherCompensation>0</OtherCompensation>
      </Form990PartVIISectionA>
      <Form990PartVIISectionA>
        <NamePerson>Dr Bob Bedford</NamePerson>
        <Title>Finance/Audit Committee</Title>
        <AverageHoursPerWeek>0.50</AverageHoursPerWeek>
        <IndividualTrusteeOrDirector>X</IndividualTrusteeOrDirector>
        <Officer>X</Officer>
        <ReportableCompFromOrganization>0</ReportableCompFromOrganization>
        <ReportableCompFromRelatedOrgs>0</ReportableCompFromRelatedOrgs>
        <OtherCompensation>0</OtherCompensation>
      </Form990PartVIISectionA>
      <Form990PartVIISectionA>
        <NamePerson>Mario Rubio</NamePerson>
        <Title>finance/Audit Committee</Title>
        <AverageHoursPerWeek>0.50</AverageHoursPerWeek>
        <IndividualTrusteeOrDirector>X</IndividualTrusteeOrDirector>
        <Officer>X</Officer>
        <ReportableCompFromOrganization>0</ReportableCompFromOrganization>
        <ReportableCompFromRelatedOrgs>0</ReportableCompFromRelatedOrgs>
        <OtherCompensation>0</OtherCompensation>
      </Form990PartVIISectionA>
      <Form990PartVIISectionA>
        <NamePerson>Heather Beaven</NamePerson>
        <Title>CEO</Title>
        <AverageHoursPerWeek>40.00</AverageHoursPerWeek>
        <IndividualTrusteeOrDirector>X</IndividualTrusteeOrDirector>
        <Officer>X</Officer>
        <ReportableCompFromOrganization>71470</ReportableCompFromOrganization>
        <ReportableCompFromRelatedOrgs>0</ReportableCompFromRelatedOrgs>
        <OtherCompensation>2542</OtherCompensation>
      </Form990PartVIISectionA>
      <Form990PartVIISectionA>
        <NamePerson>Marshall Criser</NamePerson>
        <Title>Board member</Title>
        <AverageHoursPerWeek>0.50</AverageHoursPerWeek>
        <IndividualTrusteeOrDirector>X</IndividualTrusteeOrDirector>
        <ReportableCompFromOrganization>0</ReportableCompFromOrganization>
        <ReportableCompFromRelatedOrgs>0</ReportableCompFromRelatedOrgs>
        <OtherCompensation>0</OtherCompensation>
      </Form990PartVIISectionA>
      <Form990PartVIISectionA>
        <NamePerson>Janis Schoonmaker</NamePerson>
        <Title>board member</Title>
        <AverageHoursPerWeek>0.50</AverageHoursPerWeek>
        <IndividualTrusteeOrDirector>X</IndividualTrusteeOrDirector>
        <ReportableCompFromOrganization>0</ReportableCompFromOrganization>
        <ReportableCompFromRelatedOrgs>0</ReportableCompFromRelatedOrgs>
        <OtherCompensation>0</OtherCompensation>
      </Form990PartVIISectionA>
      <Form990PartVIISectionA>
        <NamePerson>Joe Pickens</NamePerson>
        <Title>board member</Title>
        <AverageHoursPerWeek>0.50</AverageHoursPerWeek>
        <IndividualTrusteeOrDirector>X</IndividualTrusteeOrDirector>
        <ReportableCompFromOrganization>0</ReportableCompFromOrganization>
        <ReportableCompFromRelatedOrgs>0</ReportableCompFromRelatedOrgs>
        <OtherCompensation>0</OtherCompensation>
      </Form990PartVIISectionA>
      <Form990PartVIISectionA>
        <NamePerson>Emily Santos</NamePerson>
        <Title>board member</Title>
        <AverageHoursPerWeek>0.50</AverageHoursPerWeek>
        <IndividualTrusteeOrDirector>X</IndividualTrusteeOrDirector>
        <ReportableCompFromOrganization>0</ReportableCompFromOrganization>
        <ReportableCompFromRelatedOrgs>0</ReportableCompFromRelatedOrgs>
        <OtherCompensation>0</OtherCompensation>
      </Form990PartVIISectionA>
      <Form990PartVIISectionA>
        <NamePerson>Susan Lehr</NamePerson>
        <Title>board member</Title>
        <AverageHoursPerWeek>0.50</AverageHoursPerWeek>
        <IndividualTrusteeOrDirector>X</IndividualTrusteeOrDirector>
        <ReportableCompFromOrganization>0</ReportableCompFromOrganization>
        <ReportableCompFromRelatedOrgs>0</ReportableCompFromRelatedOrgs>
        <OtherCompensation>0</OtherCompensation>
      </Form990PartVIISectionA>
      <Form990PartVIISectionA>
        <NamePerson>Barney Bishop</NamePerson>
        <Title>board member</Title>
        <AverageHoursPerWeek>0.50</AverageHoursPerWeek>
        <IndividualTrusteeOrDirector>X</IndividualTrusteeOrDirector>
        <ReportableCompFromOrganization>0</ReportableCompFromOrganization>
        <ReportableCompFromRelatedOrgs>0</ReportableCompFromRelatedOrgs>
        <OtherCompensation>0</OtherCompensation>
      </Form990PartVIISectionA>
      <Form990PartVIISectionA>
        <NamePerson>Tadar Muhammad</NamePerson>
        <Title>board member</Title>
        <AverageHoursPerWeek>0.50</AverageHoursPerWeek>
        <IndividualTrusteeOrDirector>X</IndividualTrusteeOrDirector>
        <ReportableCompFromOrganization>0</ReportableCompFromOrganization>
        <ReportableCompFromRelatedOrgs>0</ReportableCompFromRelatedOrgs>
        <OtherCompensation>0</OtherCompensation>
      </Form990PartVIISectionA>
      <Form990PartVIISectionA>
        <NamePerson>Dr Gerry Meisels</NamePerson>
        <Title>board member</Title>
        <AverageHoursPerWeek>0.50</AverageHoursPerWeek>
        <IndividualTrusteeOrDirector>X</IndividualTrusteeOrDirector>
        <ReportableCompFromOrganization>0</ReportableCompFromOrganization>
        <ReportableCompFromRelatedOrgs>0</ReportableCompFromRelatedOrgs>
        <OtherCompensation>0</OtherCompensation>
      </Form990PartVIISectionA>
      <Form990PartVIISectionA>
        <NamePerson>Dr Bill Montford</NamePerson>
        <Title>board member</Title>
        <AverageHoursPerWeek>0.50</AverageHoursPerWeek>
        <IndividualTrusteeOrDirector>X</IndividualTrusteeOrDirector>
        <ReportableCompFromOrganization>0</ReportableCompFromOrganization>
        <ReportableCompFromRelatedOrgs>0</ReportableCompFromRelatedOrgs>
        <OtherCompensation>0</OtherCompensation>
      </Form990PartVIISectionA>
      <Form990PartVIISectionA>
        <NamePerson>Ellen Prager</NamePerson>
        <Title>board member</Title>
        <AverageHoursPerWeek>0.50</AverageHoursPerWeek>
        <IndividualTrusteeOrDirector>X</IndividualTrusteeOrDirector>
        <ReportableCompFromOrganization>0</ReportableCompFromOrganization>
        <ReportableCompFromRelatedOrgs>0</ReportableCompFromRelatedOrgs>
        <OtherCompensation>0</OtherCompensation>
      </Form990PartVIISectionA>
      <Form990PartVIISectionA>
        <NamePerson>Cindy M Oliver</NamePerson>
        <Title>board member</Title>
        <AverageHoursPerWeek>0.50</AverageHoursPerWeek>
        <IndividualTrusteeOrDirector>X</IndividualTrusteeOrDirector>
        <ReportableCompFromOrganization>0</ReportableCompFromOrganization>
        <ReportableCompFromRelatedOrgs>0</ReportableCompFromRelatedOrgs>
        <OtherCompensation>0</OtherCompensation>
      </Form990PartVIISectionA>
      <Form990PartVIISectionA>
        <NamePerson>Wayne Blanton</NamePerson>
        <Title>board member</Title>
        <AverageHoursPerWeek>0.50</AverageHoursPerWeek>
        <IndividualTrusteeOrDirector>X</IndividualTrusteeOrDirector>
        <ReportableCompFromOrganization>0</ReportableCompFromOrganization>
        <ReportableCompFromRelatedOrgs>0</ReportableCompFromRelatedOrgs>
        <OtherCompensation>0</OtherCompensation>
      </Form990PartVIISectionA>
      <Form990PartVIISectionA>
        <NamePerson>Lyn Stanfield</NamePerson>
        <Title>board member</Title>
        <AverageHoursPerWeek>0.50</AverageHoursPerWeek>
        <IndividualTrusteeOrDirector>X</IndividualTrusteeOrDirector>
        <ReportableCompFromOrganization>0</ReportableCompFromOrganization>
        <ReportableCompFromRelatedOrgs>0</ReportableCompFromRelatedOrgs>
        <OtherCompensation>0</OtherCompensation>
      </Form990PartVIISectionA>
      <Form990PartVIISectionA>
        <NamePerson>Skip Villerot</NamePerson>
        <Title>board member</Title>
        <AverageHoursPerWeek>0.50</AverageHoursPerWeek>
        <IndividualTrusteeOrDirector>X</IndividualTrusteeOrDirector>
        <ReportableCompFromOrganization>0</ReportableCompFromOrganization>
        <ReportableCompFromRelatedOrgs>0</ReportableCompFromRelatedOrgs>
        <OtherCompensation>0</OtherCompensation>
      </Form990PartVIISectionA>
      <Form990PartVIISectionA>
        <NamePerson>Kendra Todd</NamePerson>
        <Title>board member</Title>
        <AverageHoursPerWeek>0.50</AverageHoursPerWeek>
        <IndividualTrusteeOrDirector>X</IndividualTrusteeOrDirector>
        <ReportableCompFromOrganization>0</ReportableCompFromOrganization>
        <ReportableCompFromRelatedOrgs>0</ReportableCompFromRelatedOrgs>
        <OtherCompensation>0</OtherCompensation>
      </Form990PartVIISectionA>
      <Form990PartVIISectionA>
        <NamePerson>Lt Gov Kottkamp</NamePerson>
        <Title>EX-Officio</Title>
        <AverageHoursPerWeek>0.50</AverageHoursPerWeek>
        <IndividualTrusteeOrDirector>X</IndividualTrusteeOrDirector>
        <ReportableCompFromOrganization>0</ReportableCompFromOrganization>
        <ReportableCompFromRelatedOrgs>0</ReportableCompFromRelatedOrgs>
        <OtherCompensation>0</OtherCompensation>
      </Form990PartVIISectionA>
      <Form990PartVIISectionA>
        <NamePerson>Senator Steve Wise</NamePerson>
        <Title>eX-Officio</Title>
        <AverageHoursPerWeek>0.50</AverageHoursPerWeek>
        <IndividualTrusteeOrDirector>X</IndividualTrusteeOrDirector>
        <ReportableCompFromOrganization>0</ReportableCompFromOrganization>
        <ReportableCompFromRelatedOrgs>0</ReportableCompFromRelatedOrgs>
        <OtherCompensation>0</OtherCompensation>
      </Form990PartVIISectionA>
      <Form990PartVIISectionA>
        <NamePerson>Senator Jeremy Ring</NamePerson>
        <Title>eX-Officio</Title>
        <AverageHoursPerWeek>0.50</AverageHoursPerWeek>
        <IndividualTrusteeOrDirector>X</IndividualTrusteeOrDirector>
        <ReportableCompFromOrganization>0</ReportableCompFromOrganization>
        <ReportableCompFromRelatedOrgs>0</ReportableCompFromRelatedOrgs>
        <OtherCompensation>0</OtherCompensation>
      </Form990PartVIISectionA>
      <Form990PartVIISectionA>
        <NamePerson>Commissioner Eric Smith</NamePerson>
        <Title>eX-Officio</Title>
        <AverageHoursPerWeek>0.50</AverageHoursPerWeek>
        <IndividualTrusteeOrDirector>X</IndividualTrusteeOrDirector>
        <ReportableCompFromOrganization>0</ReportableCompFromOrganization>
        <ReportableCompFromRelatedOrgs>0</ReportableCompFromRelatedOrgs>
        <OtherCompensation>0</OtherCompensation>
      </Form990PartVIISectionA>
      <Form990PartVIISectionA>
        <NamePerson>Director Monesia Brown</NamePerson>
        <Title>eX-Officio</Title>
        <AverageHoursPerWeek>0.50</AverageHoursPerWeek>
        <IndividualTrusteeOrDirector>X</IndividualTrusteeOrDirector>
        <ReportableCompFromOrganization>0</ReportableCompFromOrganization>
        <ReportableCompFromRelatedOrgs>0</ReportableCompFromRelatedOrgs>
        <OtherCompensation>0</OtherCompensation>
      </Form990PartVIISectionA>
      <Form990PartVIISectionA>
        <NamePerson>Councilman Art Graham</NamePerson>
        <Title>eX-Officio</Title>
        <AverageHoursPerWeek>0.50</AverageHoursPerWeek>
        <IndividualTrusteeOrDirector>X</IndividualTrusteeOrDirector>
        <ReportableCompFromOrganization>0</ReportableCompFromOrganization>
        <ReportableCompFromRelatedOrgs>0</ReportableCompFromRelatedOrgs>
        <OtherCompensation>0</OtherCompensation>
      </Form990PartVIISectionA>
      <Form990PartVIISectionA>
        <NamePerson>COLLEEN WALSH CONKLIN</NamePerson>
        <Title>VP OF OPERATIONS</Title>
        <AverageHoursPerWeek>40.00</AverageHoursPerWeek>
        <Officer>X</Officer>
        <ReportableCompFromOrganization>69322</ReportableCompFromOrganization>
        <ReportableCompFromRelatedOrgs>0</ReportableCompFromRelatedOrgs>
        <OtherCompensation>0</OtherCompensation>
      </Form990PartVIISectionA>
      <Form990PartVIISectionA>
        <NamePerson>D DANIELLE NOE</NamePerson>
        <Title>VP OF ADMINISTRATION</Title>
        <AverageHoursPerWeek>40.00</AverageHoursPerWeek>
        <Officer>X</Officer>
        <ReportableCompFromOrganization>71958</ReportableCompFromOrganization>
        <ReportableCompFromRelatedOrgs>0</ReportableCompFromRelatedOrgs>
        <OtherCompensation>2542</OtherCompensation>
      </Form990PartVIISectionA>
      <TotalReportableCompFromOrg>212750</TotalReportableCompFromOrg>
      <TotalReportableCompFrmRltdOrgs>0</TotalReportableCompFrmRltdOrgs>
      <TotalOtherCompensation>5084</TotalOtherCompensation>
      <NumberIndividualsGT100K>0</NumberIndividualsGT100K>
      <FormersListed>0</FormersListed>
      <TotalCompGT150K>0</TotalCompGT150K>
      <CompensationFromOtherSources>0</CompensationFromOtherSources>
      <NumberOfContractorsGT100K>0</NumberOfContractorsGT100K>
      <GovernmentGrants>989547</GovernmentGrants>
      <AllOtherContributions>63688</AllOtherContributions>
      <TotalContributions>1053235</TotalContributions>
      <ProgramServiceRevenue>
        <Description>MATCHING REVENUE</Description>
        <BusinessCode>900099</BusinessCode>
        <TotalRevenueColumn>55500</TotalRevenueColumn>
        <RelatedOrExemptFunctionIncome>55500</RelatedOrExemptFunctionIncome>
      </ProgramServiceRevenue>
      <ProgramServiceRevenue>
        <Description>PROGRAM SERVICE FEES</Description>
        <BusinessCode>900099</BusinessCode>
        <TotalRevenueColumn>1880</TotalRevenueColumn>
        <RelatedOrExemptFunctionIncome>1880</RelatedOrExemptFunctionIncome>
      </ProgramServiceRevenue>
      <TotalProgramServiceRevenue>57380</TotalProgramServiceRevenue>
      <InvestmentIncome>
        <TotalRevenueColumn>770</TotalRevenueColumn>
        <ExclusionAmount>770</ExclusionAmount>
      </InvestmentIncome>
      <MiscellaneousRevenue>
        <TotalRevenueColumn>4178</TotalRevenueColumn>
        <RelatedOrExemptFunctionIncome>4178</RelatedOrExemptFunctionIncome>
      </MiscellaneousRevenue>
      <TotalOtherRevenue>4178</TotalOtherRevenue>
      <TotalRevenue>
        <TotalRevenueColumn>1115563</TotalRevenueColumn>
        <RelatedOrExemptFunctionIncome>61558</RelatedOrExemptFunctionIncome>
        <UnrelatedBusinessRevenue>0</UnrelatedBusinessRevenue>
        <ExclusionAmount>770</ExclusionAmount>
      </TotalRevenue>
      <CompCurrentOfficersDirectors>
        <Total>228779</Total>
        <ProgramServices>116677</ProgramServices>
        <ManagementAndGeneral>112102</ManagementAndGeneral>
      </CompCurrentOfficersDirectors>
      <OtherSalariesAndWages>
        <Total>630677</Total>
        <ProgramServices>589832</ProgramServices>
        <ManagementAndGeneral>29312</ManagementAndGeneral>
        <Fundraising>11533</Fundraising>
      </OtherSalariesAndWages>
      <OtherEmployeeBenefits>
        <Total>36672</Total>
        <ProgramServices>29382</ProgramServices>
        <ManagementAndGeneral>6791</ManagementAndGeneral>
        <Fundraising>499</Fundraising>
      </OtherEmployeeBenefits>
      <PayrollTaxes>
        <Total>77045</Total>
        <ProgramServices>63177</ProgramServices>
        <ManagementAndGeneral>12328</ManagementAndGeneral>
        <Fundraising>1540</Fundraising>
      </PayrollTaxes>
      <FeesForServicesLegal>
        <Total>1152</Total>
        <ProgramServices>979</ProgramServices>
        <ManagementAndGeneral>173</ManagementAndGeneral>
      </FeesForServicesLegal>
      <FeesForServicesAccounting>
        <Total>24600</Total>
        <ProgramServices>24600</ProgramServices>
      </FeesForServicesAccounting>
      <FeesForServicesOther>
        <Total>31581</Total>
        <ProgramServices>28263</ProgramServices>
        <ManagementAndGeneral>3318</ManagementAndGeneral>
      </FeesForServicesOther>
      <OfficeExpenses>
        <Total>9765</Total>
        <ProgramServices>9149</ProgramServices>
        <ManagementAndGeneral>591</ManagementAndGeneral>
        <Fundraising>25</Fundraising>
      </OfficeExpenses>
      <Occupancy>
        <Total>13950</Total>
        <ProgramServices>11160</ProgramServices>
        <ManagementAndGeneral>2790</ManagementAndGeneral>
      </Occupancy>
      <Travel>
        <Total>11281</Total>
        <ProgramServices>6359</ProgramServices>
        <ManagementAndGeneral>4417</ManagementAndGeneral>
        <Fundraising>505</Fundraising>
      </Travel>
      <ConferencesMeetings>
        <Total>13095</Total>
        <ProgramServices>12931</ProgramServices>
        <ManagementAndGeneral>75</ManagementAndGeneral>
        <Fundraising>89</Fundraising>
      </ConferencesMeetings>
      <Interest>
        <Total>49</Total>
        <ManagementAndGeneral>49</ManagementAndGeneral>
      </Interest>
      <DepreciationDepletion>
        <Total>4105</Total>
        <ManagementAndGeneral>4105</ManagementAndGeneral>
      </DepreciationDepletion>
      <Insurance>
        <Total>12133</Total>
        <ProgramServices>10725</ProgramServices>
        <ManagementAndGeneral>1408</ManagementAndGeneral>
      </Insurance>
      <OtherExpenses>
        <Description>Contract Services</Description>
        <Total>132281</Total>
        <ProgramServices>132281</ProgramServices>
      </OtherExpenses>
      <OtherExpenses>
        <Description>marketing</Description>
        <Total>24168</Total>
        <ProgramServices>24168</ProgramServices>
      </OtherExpenses>
      <OtherExpenses>
        <Description>membership/affiliation</Description>
        <Total>18000</Total>
        <ProgramServices>17850</ProgramServices>
        <ManagementAndGeneral>150</ManagementAndGeneral>
      </OtherExpenses>
      <OtherExpenses>
        <Description>TELEPHONE</Description>
        <Total>4362</Total>
        <ProgramServices>3555</ProgramServices>
        <ManagementAndGeneral>807</ManagementAndGeneral>
      </OtherExpenses>
      <OtherExpenses>
        <Description>PRINTING AND PUBLICATIO</Description>
        <Total>2793</Total>
        <ProgramServices>2595</ProgramServices>
        <ManagementAndGeneral>182</ManagementAndGeneral>
        <Fundraising>16</Fundraising>
      </OtherExpenses>
      <AllOtherExpenses>
        <Total>5909</Total>
        <ProgramServices>2862</ProgramServices>
        <ManagementAndGeneral>823</ManagementAndGeneral>
        <Fundraising>2224</Fundraising>
      </AllOtherExpenses>
      <TotalFunctionalExpenses>
        <Total>1282397</Total>
        <ProgramServices>1086545</ProgramServices>
        <ManagementAndGeneral>179421</ManagementAndGeneral>
        <Fundraising>16431</Fundraising>
      </TotalFunctionalExpenses>
      <CashNonInterestBearing>
        <EOY>277</EOY>
      </CashNonInterestBearing>
      <SavingsAndTempCashInvestments>
        <BOY>231519</BOY>
        <EOY>98107</EOY>
      </SavingsAndTempCashInvestments>
      <PledgesAndGrantsReceivable>
        <BOY>119252</BOY>
        <EOY>134023</EOY>
      </PledgesAndGrantsReceivable>
      <LandBuildingsEquipmentBasis>42499</LandBuildingsEquipmentBasis>
      <LandBldgEquipmentAccumDeprec>8210</LandBldgEquipmentAccumDeprec>
      <LandBuildingsEquipmentBasisNet>
        <BOY>38394</BOY>
        <EOY>34289</EOY>
      </LandBuildingsEquipmentBasisNet>
      <OtherAssetsTotal>
        <BOY>1460</BOY>
        <EOY>1460</EOY>
      </OtherAssetsTotal>
      <TotalAssets>
        <BOY>390625</BOY>
        <EOY>268156</EOY>
      </TotalAssets>
      <AccountsPayableAccruedExpenses>
        <BOY>25904</BOY>
        <EOY>31454</EOY>
      </AccountsPayableAccruedExpenses>
      <MortNotesPyblSecuredInvestProp>
        <EOY>38815</EOY>
      </MortNotesPyblSecuredInvestProp>
      <TotalLiabilities>
        <BOY>25904</BOY>
        <EOY>70269</EOY>
      </TotalLiabilities>
      <FollowSFAS117>X</FollowSFAS117>
      <UnrestrictedNetAssets>
        <BOY>364721</BOY>
        <EOY>197887</EOY>
      </UnrestrictedNetAssets>
      <TotalNetAssetsFundBalances>
        <BOY>364721</BOY>
        <EOY>197887</EOY>
      </TotalNetAssetsFundBalances>
      <TotalLiabNetAssetsFundBalances>
        <BOY>390625</BOY>
        <EOY>268156</EOY>
      </TotalLiabNetAssetsFundBalances>
      <MethodOfAccountingAccrual>X</MethodOfAccountingAccrual>
      <AccountantCompileOrReview>0</AccountantCompileOrReview>
      <FSAudited>1</FSAudited>
      <AuditCommittee>1</AuditCommittee>
      <FinancialStatementSeparate>X</FinancialStatementSeparate>
      <FederalGrantAuditRequired>0</FederalGrantAuditRequired>
    </IRS990>
    <IRS990ScheduleA documentId="RetDoc1039100001">
      <PubliclySupportedOrg170b1Avi>X</PubliclySupportedOrg170b1Avi>
      <GiftsGrantsContribReceived170>
        <CurrentTaxYearMinus4Years>116141</CurrentTaxYearMinus4Years>
        <CurrentTaxYearMinus3Years>120895</CurrentTaxYearMinus3Years>
        <CurrentTaxYearMinus2Years>1387500</CurrentTaxYearMinus2Years>
        <CurrentTaxYearMinus1Year>1681053</CurrentTaxYearMinus1Year>
        <CurrentTaxYear>1055115</CurrentTaxYear>
        <Total>4360704</Total>
      </GiftsGrantsContribReceived170>
      <Total170>
        <CurrentTaxYearMinus4Years>116141</CurrentTaxYearMinus4Years>
        <CurrentTaxYearMinus3Years>120895</CurrentTaxYearMinus3Years>
        <CurrentTaxYearMinus2Years>1387500</CurrentTaxYearMinus2Years>
        <CurrentTaxYearMinus1Year>1681053</CurrentTaxYearMinus1Year>
        <CurrentTaxYear>1055115</CurrentTaxYear>
        <Total>4360704</Total>
      </Total170>
      <PublicSupportTotal170>4360704</PublicSupportTotal170>
      <GrossInvestmentIncome170>
        <CurrentTaxYearMinus2Years>2003</CurrentTaxYearMinus2Years>
        <CurrentTaxYearMinus1Year>3222</CurrentTaxYearMinus1Year>
        <CurrentTaxYear>770</CurrentTaxYear>
        <Total>5995</Total>
      </GrossInvestmentIncome170>
      <OtherIncome170>
        <CurrentTaxYearMinus2Years>55000</CurrentTaxYearMinus2Years>
        <CurrentTaxYearMinus1Year>97247</CurrentTaxYearMinus1Year>
        <CurrentTaxYear>59678</CurrentTaxYear>
        <Total>211925</Total>
      </OtherIncome170>
      <TotalSupport>4578624</TotalSupport>
      <PublicSupportPertcentage170>0.95240</PublicSupportPertcentage170>
      <PublicSupportPertcentPriorYear>0.94330</PublicSupportPertcentPriorYear>
      <ThirtyThreePercntTestsCY170>X</ThirtyThreePercntTestsCY170>
      <GeneralExplanation>Schedule A, Part IV, Supplemental Information: SCHEDULE A, PART II, LINE 10, DESCRIPTION OF OTHER INCOME: MATCHING REVENUE - $55,500 OTHER REVENUE - $ 4,178</GeneralExplanation>
    </IRS990ScheduleA>
    <IRS990ScheduleB documentId="RetDoc1234500001">
      <ContributorInfo>
        <ContributorNumber>RESTRICTED</ContributorNumber>
        <ContributorNameBusiness>
          <BusinessNameLine1>RESTRICTED</BusinessNameLine1>
        </ContributorNameBusiness>
        <ContributorAddressUS>
          <AddressLine1>RESTRICTED</AddressLine1>
          <AddressLine2>RESTRICTED</AddressLine2>
          <City>RESTRICTED</City>
          <State>RESTRICTED</State>
          <ZIPCode>RESTRICTED</ZIPCode>
        </ContributorAddressUS>
        <AggregateContributions>RESTRICTED</AggregateContributions>
      </ContributorInfo>
    </IRS990ScheduleB>
    <IRS990ScheduleD documentId="RetDoc1040000001">
      <Land>
        <InvestmentCostOrOtherBasis>30183</InvestmentCostOrOtherBasis>
        <BookValue>30183</BookValue>
      </Land>
      <Equipment>
        <InvestmentCostOrOtherBasis>12316</InvestmentCostOrOtherBasis>
        <Depreciation>8210</Depreciation>
        <BookValue>4106</BookValue>
      </Equipment>
      <TotalOfBookValueLandBuildings>34289</TotalOfBookValueLandBuildings>
      <TotalRevenue>1115563</TotalRevenue>
      <TotalExpenses>1282397</TotalExpenses>
      <ExcessOrDeficitForYear>-166834</ExcessOrDeficitForYear>
      <TotalAdjustments>0</TotalAdjustments>
      <ExcessOrDeficitPerFS>-166834</ExcessOrDeficitPerFS>
      <TotRevenueEtcAuditedFinclStmt>1115563</TotRevenueEtcAuditedFinclStmt>
      <RevenueNotRptdF990>0</RevenueNotRptdF990>
      <RevenueSubtotal>1115563</RevenueSubtotal>
      <RevenueNotRptdOnFinStmt>0</RevenueNotRptdOnFinStmt>
      <TotalRevenuePerForm990>1115563</TotalRevenuePerForm990>
      <TotExpensesEtcAuditedFinclStmt>1282397</TotExpensesEtcAuditedFinclStmt>
      <ExpensesNotRptdF990>0</ExpensesNotRptdF990>
      <ExpensesSubtotal>1282397</ExpensesSubtotal>
      <ExpensesNotRptdOnFinStmt>0</ExpensesNotRptdOnFinStmt>
      <TotalExpensesPerForm990>1282397</TotalExpensesPerForm990>
    </IRS990ScheduleD>
    <IRS990ScheduleO documentId="RetDoc1044400001">
      <GeneralExplanation>
        <Identifier>Form 990, Part VI, Section B, line 11</Identifier>
        <Explanation>when form 990 is finalized the form is submitted for review to the board of directors prior to filing.</Explanation>
      </GeneralExplanation>
      <GeneralExplanation>
        <Identifier>Form 990, Part VI, Section B, line 12c</Identifier>
        <Explanation>In connection with any actual or possible conflict of interest, an interested person must disclose the existence of the financial interest and be given the opportunity to disclose all material facts to the directors and members of committees with governing board delegated powers considering the proposed transaction or arrangement. After disclosure of the financial interest and all material facts, and after any discussion with the interested person, he/she shall leave the Board meeting while the determination of a conflict of interest is discussed and voted upon. If the Board has reasonable cause to believe a member has failed to disclose actual or possible conflict of interest, it shall inform the member of the basis for such belief and afford the member an opportunity to explain the alleged failure to disclose. If, after hearing the Director's response and after making further investigation as warranted by the circumstances, the Board determines the member has failed to disclose an actual or possible conflict of interest, it shall take appropriate corrective action as voted on by the Board.</Explanation>
      </GeneralExplanation>
      <GeneralExplanation>
        <Identifier>Form 990, Part VI, Section B, line 15</Identifier>
        <Explanation>The compensation of Organization's CEO and top management officials is approved by the board of directors and monitored as a part of the budgeting process.</Explanation>
      </GeneralExplanation>
      <GeneralExplanation>
        <Identifier>Form 990, Part VI, Section C, line 19</Identifier>
        <Explanation>Organization's governing documents and financial statements are available for public inspection upon request at their office in Flagler Beach at 306 S. Oceanshore blvd.</Explanation>
      </GeneralExplanation>
      <GeneralExplanation>
        <Identifier>FORM 990, PART XI, LINC 2C</Identifier>
        <Explanation>THERE HAVE BEEN NO CHANGES SINCE THE PRIOR YEAR.</Explanation>
      </GeneralExplanation>
    </IRS990ScheduleO>
  </ReturnData>
</Return>