<?xml version="1.0" encoding="utf-8"?>
<Return xmlns="http://www.irs.gov/efile" xmlns:xsi="http://www.w3.org/2001/XMLSchema-instance" returnVersion="2010v3.2" xsi:schemaLocation="http://www.irs.gov/efile">
  <ReturnHeader binaryAttachmentCount="0">
    <Timestamp>2011-02-26T10:27:00-08:00</Timestamp>
    <TaxPeriodEndDate>2010-12-31</TaxPeriodEndDate>
    <PreparerFirm>
      <PreparerFirmBusinessName>
        <BusinessNameLine1>MADDOX &amp; ASSOCIATES APC</BusinessNameLine1>
      </PreparerFirmBusinessName>
      <PreparerFirmUSAddress>
        <AddressLine1>5627 BANKERS AVE BLDG 2</AddressLine1>
        <City>BATON ROUGE</City>
        <State>LA</State>
        <ZIPCode>708082610</ZIPCode>
      </PreparerFirmUSAddress>
    </PreparerFirm>
    <ReturnType>990</ReturnType>
    <TaxPeriodBeginDate>2010-01-01</TaxPeriodBeginDate>
    <Filer>
      <EIN>830240068</EIN>
      <Name>
        <BusinessNameLine1>HERITAGE TOWERS OF THE CHRISTIAN CHURCH</BusinessNameLine1>
        <BusinessNameLine2>DISCIPLES OF CHRIST</BusinessNameLine2>
      </Name>
      <NameControl>HERI</NameControl>
      <Phone>3076748825</Phone>
      <USAddress>
        <AddressLine1>428 N JEFFERSON STREET</AddressLine1>
        <City>SHERIDAN</City>
        <State>WY</State>
        <ZIPCode>82801</ZIPCode>
      </USAddress>
    </Filer>
    <Officer>
      <Name>CLARENCE MONTANO</Name>
      <Title>President</Title>
      <DateSigned>2011-02-26</DateSigned>
    </Officer>
    <Preparer>
      <Name>WILLIAM B BEALE</Name>
      <Phone>2259263360</Phone>
    </Preparer>
    <TaxYear>2010</TaxYear>
    <BuildTS>2016-02-24 21:20:13Z</BuildTS>
  </ReturnHeader>
  <ReturnData documentCount="4">
    <IRS990 documentId="IRS990" referenceDocumentId=" IRS990ScheduleO" softwareId="10000105" softwareVersion="2010v3.2">
      <GrossReceipts>633586</GrossReceipts>
      <GroupReturnForAffiliates>false</GroupReturnForAffiliates>
      <AllAffiliatesIncluded>false</AllAffiliatesIncluded>
      <GroupExemptionNumber>1125</GroupExemptionNumber>
      <Organization501c3>X</Organization501c3>
      <WebSite>N/A</WebSite>
      <TypeOfOrganizationCorporation>X</TypeOfOrganizationCorporation>
      <YearFormation>1977</YearFormation>
      <StateLegalDomicile>WY</StateLegalDomicile>
      <ActivityOrMissionDescription>PROVIDES HOUSING TO LOW INCOME ELDERLY PERSONS UNDER SECTION 202 OF THE NATIONAL HOUSING ACT UNDER AGREEMENT WITH THE DEPARTMENT OF HUD.</ActivityOrMissionDescription>
      <NbrVotingMembersGoverningBody>10</NbrVotingMembersGoverningBody>
      <NbrIndependentVotingMembers>10</NbrIndependentVotingMembers>
      <TotalNbrEmployees>0</TotalNbrEmployees>
      <TotalGrossUBI>0</TotalGrossUBI>
      <ContributionsGrantsCurrentYear>0</ContributionsGrantsCurrentYear>
      <ProgramServiceRevenuePriorYear>631991</ProgramServiceRevenuePriorYear>
      <ProgramServiceRevenueCY>631383</ProgramServiceRevenueCY>
      <InvestmentIncomePriorYear>3610</InvestmentIncomePriorYear>
      <InvestmentIncomeCurrentYear>2203</InvestmentIncomeCurrentYear>
      <OtherRevenueCurrentYear>0</OtherRevenueCurrentYear>
      <TotalRevenuePriorYear>635601</TotalRevenuePriorYear>
      <TotalRevenueCurrentYear>633586</TotalRevenueCurrentYear>
      <GrantsAndSimilarAmntsCY>0</GrantsAndSimilarAmntsCY>
      <BenefitsPaidToMembersCY>0</BenefitsPaidToMembersCY>
      <SalariesEtcPriorYear>167623</SalariesEtcPriorYear>
      <SalariesEtcCurrentYear>181579</SalariesEtcCurrentYear>
      <TotalProfFundrsngExpCY>0</TotalProfFundrsngExpCY>
      <TotalFundrsngExpCurrentYear>0</TotalFundrsngExpCurrentYear>
      <OtherExpensePriorYear>475608</OtherExpensePriorYear>
      <OtherExpensesCurrentYear>515128</OtherExpensesCurrentYear>
      <TotalExpensesPriorYear>643231</TotalExpensesPriorYear>
      <TotalExpensesCurrentYear>696707</TotalExpensesCurrentYear>
      <RevenuesLessExpensesPriorYear>-7630</RevenuesLessExpensesPriorYear>
      <RevenuesLessExpensesCY>-63121</RevenuesLessExpensesCY>
      <TotalAssetsBOY>2353127</TotalAssetsBOY>
      <TotalAssetsEOY>2257354</TotalAssetsEOY>
      <TotalLiabilitiesBOY>2219896</TotalLiabilitiesBOY>
      <TotalLiabilitiesEOY>2187244</TotalLiabilitiesEOY>
      <NetAssetsOrFundBalancesBOY>133231</NetAssetsOrFundBalancesBOY>
      <NetAssetsOrFundBalancesEOY>70110</NetAssetsOrFundBalancesEOY>
      <MissionDescription>PROVIDES HOUSING TO LOW INCOME ELDERLY PERSONS UNDER SECTION 202 OF THE NATIONAL HOUSING ACT UNDER AGREEMENT WITH THE DEPARTMENT OF HUD.</MissionDescription>
      <SignificantNewProgramServices>false</SignificantNewProgramServices>
      <SignificantChange>false</SignificantChange>
      <Expense>684237</Expense>
      <Revenue>596147</Revenue>
      <Description>PROVIDES HOUSING TO LOW INCOME ELDERLY PERSONS UNDER SECTION 202 OF THE NATIONAL HOUSING ACT UNDER AGREEMENT WITH THE DEPARTMENT OF HUD.</Description>
      <TotalProgramServiceExpense>684237</TotalProgramServiceExpense>
      <DescribedIn501C3 referenceDocumentId=" IRS990ScheduleA">true</DescribedIn501C3>
      <ScheduleBRequired>false</ScheduleBRequired>
      <PoliticalActivities>false</PoliticalActivities>
      <LobbyingActivities>false</LobbyingActivities>
      <SubjectToProxyTax>false</SubjectToProxyTax>
      <DonorAdvisedFunds referenceDocumentId=" IRS990ScheduleD">false</DonorAdvisedFunds>
      <ConservationEasements referenceDocumentId=" IRS990ScheduleD">false</ConservationEasements>
      <CollectionsOfArt referenceDocumentId=" IRS990ScheduleD">false</CollectionsOfArt>
      <CreditCounseling referenceDocumentId=" IRS990ScheduleD">false</CreditCounseling>
      <TermOrPermanentEndowments referenceDocumentId=" IRS990ScheduleD">false</TermOrPermanentEndowments>
      <ReportLandBldgEquip referenceDocumentId=" IRS990ScheduleD">true</ReportLandBldgEquip>
      <ReportInvestOthSecurities referenceDocumentId=" IRS990ScheduleD">false</ReportInvestOthSecurities>
      <ReportProgRelInvest referenceDocumentId=" IRS990ScheduleD">false</ReportProgRelInvest>
      <ReportOtherAssets referenceDocumentId=" IRS990ScheduleD">true</ReportOtherAssets>
      <ReportOtherLiabilities referenceDocumentId=" IRS990ScheduleD">true</ReportOtherLiabilities>
      <ReportFin48Footnote referenceDocumentId=" IRS990ScheduleD">false</ReportFin48Footnote>
      <IndependentAuditFinancialStmt referenceDocumentId=" IRS990ScheduleD">true</IndependentAuditFinancialStmt>
      <ConsolidatedAuditFinancialStmt referenceDocumentId=" IRS990ScheduleD">false</ConsolidatedAuditFinancialStmt>
      <School>false</School>
      <ForeignOffice>false</ForeignOffice>
      <ForeignActivities>false</ForeignActivities>
      <MoreThan5000KToOrganizations>false</MoreThan5000KToOrganizations>
      <MoreThan5000KToIndividuals>false</MoreThan5000KToIndividuals>
      <ProfessionalFundraising>false</ProfessionalFundraising>
      <FundraisingActivities>false</FundraisingActivities>
      <Gaming>false</Gaming>
      <Hospital>false</Hospital>
      <GrantsToOrganizations>false</GrantsToOrganizations>
      <GrantsToIndividuals>false</GrantsToIndividuals>
      <ScheduleJRequired>false</ScheduleJRequired>
      <TaxExemptBonds>false</TaxExemptBonds>
      <InvestTaxExemptBonds>false</InvestTaxExemptBonds>
      <EscrowAccount>false</EscrowAccount>
      <OnBehalfOfIssuer>false</OnBehalfOfIssuer>
      <ExcessBenefitTransaction>false</ExcessBenefitTransaction>
      <PriorExcessBenefitTransaction>false</PriorExcessBenefitTransaction>
      <LoanToOfficerOrDQP>false</LoanToOfficerOrDQP>
      <GrantToRelatedPerson>false</GrantToRelatedPerson>
      <BsnssRltnshpWithOrganization>false</BsnssRltnshpWithOrganization>
      <BsnssRltnshpThruFamilyMember>false</BsnssRltnshpThruFamilyMember>
      <OfficerEntityWithBsnssRltnshp>false</OfficerEntityWithBsnssRltnshp>
      <DeductibleNonCashContributions>false</DeductibleNonCashContributions>
      <DeductibleContributionsOfArt>false</DeductibleContributionsOfArt>
      <Terminated>false</Terminated>
      <PartialLiquidation>false</PartialLiquidation>
      <DisregardedEntity>false</DisregardedEntity>
      <RelatedEntity>false</RelatedEntity>
      <RelatedOrgControlledEntity>false</RelatedOrgControlledEntity>
      <TransactionRelatedEntity>false</TransactionRelatedEntity>
      <TransfersToExemptNonChrtblOrg>false</TransfersToExemptNonChrtblOrg>
      <ActivitiesConductedPartnership>false</ActivitiesConductedPartnership>
      <ScheduleORequired>false</ScheduleORequired>
      <NumberFormsTransmittedWith1096>0</NumberFormsTransmittedWith1096>
      <NumberW2GIncluded>0</NumberW2GIncluded>
      <ComplianceWithBackupWitholding>false</ComplianceWithBackupWitholding>
      <NumberOfEmployees>0</NumberOfEmployees>
      <EmploymentTaxReturnsFiled>false</EmploymentTaxReturnsFiled>
      <UnrelatedBusinessIncome>false</UnrelatedBusinessIncome>
      <Form990-TFiled>false</Form990-TFiled>
      <ForeignFinancialAccount>false</ForeignFinancialAccount>
      <ProhibitedTaxShelterTrans>false</ProhibitedTaxShelterTrans>
      <TaxablePartyNotification>false</TaxablePartyNotification>
      <Form8886TFiled>false</Form8886TFiled>
      <NonDeductibleContributions>false</NonDeductibleContributions>
      <NonDeductibleDisclosure>false</NonDeductibleDisclosure>
      <QuidProQuoContributions>false</QuidProQuoContributions>
      <QuidProQuoDisclosure>false</QuidProQuoDisclosure>
      <Form8282PropertyDisposedOf>false</Form8282PropertyDisposedOf>
      <NumberOf8282Filed>0</NumberOf8282Filed>
      <FundsToPayPremiums>false</FundsToPayPremiums>
      <PremiumsPaid>false</PremiumsPaid>
      <Form8899Filed>false</Form8899Filed>
      <Form1098CFiled>false</Form1098CFiled>
      <ExcessBusinessHoldings>false</ExcessBusinessHoldings>
      <TaxableDistributions>false</TaxableDistributions>
      <DistributionToDonor>false</DistributionToDonor>
      <FiledLieu1041>false</FiledLieu1041>
      <LicensedMoreThanOneState>false</LicensedMoreThanOneState>
      <IndoorTanningServices>false</IndoorTanningServices>
      <Form720Filed>false</Form720Filed>
      <InfoInScheduleOPartVI>X</InfoInScheduleOPartVI>
      <NbrVotingGoverningBodyMembers>10</NbrVotingGoverningBodyMembers>
      <NumberIndependentVotingMembers>10</NumberIndependentVotingMembers>
      <FamilyOrBusinessRelationship>false</FamilyOrBusinessRelationship>
      <DelegationOfManagementDuties>false</DelegationOfManagementDuties>
      <ChangesToOrganizingDocs>false</ChangesToOrganizingDocs>
      <MaterialDiversionOrMisuse>false</MaterialDiversionOrMisuse>
      <MembersOrStockholders>false</MembersOrStockholders>
      <ElectionOfBoardMembers>true</ElectionOfBoardMembers>
      <DecisionsSubjectToApproval>true</DecisionsSubjectToApproval>
      <MinutesOfGoverningBody>true</MinutesOfGoverningBody>
      <MinutesOfCommittees>true</MinutesOfCommittees>
      <OfficerMailingAddress>false</OfficerMailingAddress>
      <LocalChapters>false</LocalChapters>
      <PoliciesReferenceChapters>false</PoliciesReferenceChapters>
      <Form990ProvidedToGoverningBody>false</Form990ProvidedToGoverningBody>
      <ConflictOfInterestPolicy>true</ConflictOfInterestPolicy>
      <AnnualDisclosureCoveredPersons>false</AnnualDisclosureCoveredPersons>
      <RegularMonitoringEnforcement>false</RegularMonitoringEnforcement>
      <WhistleblowerPolicy>true</WhistleblowerPolicy>
      <DocumentRetentionPolicy>true</DocumentRetentionPolicy>
      <CompensationProcessCEO>false</CompensationProcessCEO>
      <CompensationProcessOther>false</CompensationProcessOther>
      <InvestmentInJointVenture>false</InvestmentInJointVenture>
      <WrittenPolicyOrProcedure>false</WrittenPolicyOrProcedure>
      <UponRequest>X</UponRequest>
      <TheBooksAreInCareOf>
        <NamePerson>HERITAGE TOWERS OF THE CHRISTI</NamePerson>
        <TelephoneNumber>3076748825</TelephoneNumber>
        <AddressUS>
          <AddressLine1>428 N JEFFERSON STREET</AddressLine1>
          <City>SHERIDAN</City>
          <State>WY</State>
          <ZIPCode>828013860</ZIPCode>
        </AddressUS>
      </TheBooksAreInCareOf>
      <NoListedPersonsCompensated>X</NoListedPersonsCompensated>
      <Form990PartVIISectionA>
        <NamePerson>ZACHARY GRAY</NamePerson>
        <Title>Director</Title>
        <AverageHoursPerWeek>0.00</AverageHoursPerWeek>
        <IndividualTrusteeOrDirector>X</IndividualTrusteeOrDirector>
        <ReportableCompFromOrganization>0</ReportableCompFromOrganization>
        <ReportableCompFromRelatedOrgs>0</ReportableCompFromRelatedOrgs>
        <OtherCompensation>0</OtherCompensation>
      </Form990PartVIISectionA>
      <Form990PartVIISectionA>
        <NamePerson>THOMAS DIXON</NamePerson>
        <Title>Secretary</Title>
        <AverageHoursPerWeek>0.00</AverageHoursPerWeek>
        <IndividualTrusteeOrDirector>X</IndividualTrusteeOrDirector>
        <ReportableCompFromOrganization>0</ReportableCompFromOrganization>
        <ReportableCompFromRelatedOrgs>0</ReportableCompFromRelatedOrgs>
        <OtherCompensation>0</OtherCompensation>
      </Form990PartVIISectionA>
      <Form990PartVIISectionA>
        <NamePerson>PHIL WOLD</NamePerson>
        <Title>Director</Title>
        <AverageHoursPerWeek>0.00</AverageHoursPerWeek>
        <IndividualTrusteeOrDirector>X</IndividualTrusteeOrDirector>
        <ReportableCompFromOrganization>0</ReportableCompFromOrganization>
        <ReportableCompFromRelatedOrgs>0</ReportableCompFromRelatedOrgs>
        <OtherCompensation>0</OtherCompensation>
      </Form990PartVIISectionA>
      <Form990PartVIISectionA>
        <NamePerson>LINDA KROUT</NamePerson>
        <Title>Director</Title>
        <AverageHoursPerWeek>0.00</AverageHoursPerWeek>
        <IndividualTrusteeOrDirector>X</IndividualTrusteeOrDirector>
        <ReportableCompFromOrganization>0</ReportableCompFromOrganization>
        <ReportableCompFromRelatedOrgs>0</ReportableCompFromRelatedOrgs>
        <OtherCompensation>0</OtherCompensation>
      </Form990PartVIISectionA>
      <Form990PartVIISectionA>
        <NamePerson>LEE INGALLS</NamePerson>
        <Title>Vice President</Title>
        <AverageHoursPerWeek>0.00</AverageHoursPerWeek>
        <Officer>X</Officer>
        <ReportableCompFromOrganization>0</ReportableCompFromOrganization>
        <ReportableCompFromRelatedOrgs>0</ReportableCompFromRelatedOrgs>
        <OtherCompensation>0</OtherCompensation>
      </Form990PartVIISectionA>
      <Form990PartVIISectionA>
        <NamePerson>KENNNETH HUMPHREY</NamePerson>
        <Title>ADMINISTRATOR</Title>
        <AverageHoursPerWeek>0.00</AverageHoursPerWeek>
        <ReportableCompFromOrganization>0</ReportableCompFromOrganization>
        <ReportableCompFromRelatedOrgs>0</ReportableCompFromRelatedOrgs>
        <OtherCompensation>0</OtherCompensation>
      </Form990PartVIISectionA>
      <Form990PartVIISectionA>
        <NamePerson>JIM WILSON</NamePerson>
        <Title>Director</Title>
        <AverageHoursPerWeek>0.00</AverageHoursPerWeek>
        <IndividualTrusteeOrDirector>X</IndividualTrusteeOrDirector>
        <ReportableCompFromOrganization>0</ReportableCompFromOrganization>
        <ReportableCompFromRelatedOrgs>0</ReportableCompFromRelatedOrgs>
        <OtherCompensation>0</OtherCompensation>
      </Form990PartVIISectionA>
      <Form990PartVIISectionA>
        <NamePerson>JERRY O'DANIELS</NamePerson>
        <Title>Director</Title>
        <AverageHoursPerWeek>0.00</AverageHoursPerWeek>
        <IndividualTrusteeOrDirector>X</IndividualTrusteeOrDirector>
        <ReportableCompFromOrganization>0</ReportableCompFromOrganization>
        <ReportableCompFromRelatedOrgs>0</ReportableCompFromRelatedOrgs>
        <OtherCompensation>0</OtherCompensation>
      </Form990PartVIISectionA>
      <Form990PartVIISectionA>
        <NamePerson>DON DERRYBERRY</NamePerson>
        <Title>Secretary</Title>
        <AverageHoursPerWeek>0.00</AverageHoursPerWeek>
        <Officer>X</Officer>
        <ReportableCompFromOrganization>0</ReportableCompFromOrganization>
        <ReportableCompFromRelatedOrgs>0</ReportableCompFromRelatedOrgs>
        <OtherCompensation>0</OtherCompensation>
      </Form990PartVIISectionA>
      <Form990PartVIISectionA>
        <NamePerson>CLARENCE MONTANO</NamePerson>
        <Title>President</Title>
        <AverageHoursPerWeek>0.00</AverageHoursPerWeek>
        <Officer>X</Officer>
        <ReportableCompFromOrganization>0</ReportableCompFromOrganization>
        <ReportableCompFromRelatedOrgs>0</ReportableCompFromRelatedOrgs>
        <OtherCompensation>0</OtherCompensation>
      </Form990PartVIISectionA>
      <NumberIndividualsGT100K>0</NumberIndividualsGT100K>
      <FormersListed>false</FormersListed>
      <TotalCompGT150K>false</TotalCompGT150K>
      <CompensationFromOtherSources>false</CompensationFromOtherSources>
      <NumberOfContractorsGT100K>0</NumberOfContractorsGT100K>
      <TotalContributions>0</TotalContributions>
      <ProgramServiceRevenue>
        <Description>SERVICE COORDINATOR</Description>
        <TotalRevenueColumn>35236</TotalRevenueColumn>
        <RelatedOrExemptFunctionIncome>35236</RelatedOrExemptFunctionIncome>
      </ProgramServiceRevenue>
      <ProgramServiceRevenue>
        <Description>RENTAL OF HSG TO ELDERLY</Description>
        <TotalRevenueColumn>596147</TotalRevenueColumn>
        <RelatedOrExemptFunctionIncome>596147</RelatedOrExemptFunctionIncome>
      </ProgramServiceRevenue>
      <TotalProgramServiceRevenue>631383</TotalProgramServiceRevenue>
      <InvestmentIncome>
        <TotalRevenueColumn>2203</TotalRevenueColumn>
        <RelatedOrExemptFunctionIncome>2203</RelatedOrExemptFunctionIncome>
      </InvestmentIncome>
      <IncomeFromInvestBondProceeds>
        <TotalRevenueColumn>0</TotalRevenueColumn>
      </IncomeFromInvestBondProceeds>
      <RoyaltiesRevenue>
        <TotalRevenueColumn>0</TotalRevenueColumn>
      </RoyaltiesRevenue>
      <NetRentalIncomeOrLoss>
        <TotalRevenueColumn>0</TotalRevenueColumn>
      </NetRentalIncomeOrLoss>
      <NetGainOrLossInvestments>
        <TotalRevenueColumn>0</TotalRevenueColumn>
      </NetGainOrLossInvestments>
      <NetIncomeFromFundraisingEvents>
        <TotalRevenueColumn>0</TotalRevenueColumn>
      </NetIncomeFromFundraisingEvents>
      <NetIncomeFromGaming>
        <TotalRevenueColumn>0</TotalRevenueColumn>
      </NetIncomeFromGaming>
      <NetIncomeOrLoss>
        <TotalRevenueColumn>0</TotalRevenueColumn>
      </NetIncomeOrLoss>
      <TotalOtherRevenue>0</TotalOtherRevenue>
      <TotalRevenue>
        <TotalRevenueColumn>633586</TotalRevenueColumn>
        <RelatedOrExemptFunctionIncome>633586</RelatedOrExemptFunctionIncome>
      </TotalRevenue>
      <GrantsToDomesticOrgs>
        <Total>0</Total>
      </GrantsToDomesticOrgs>
      <GrantsToDomesticIndividuals>
        <Total>0</Total>
      </GrantsToDomesticIndividuals>
      <ForeignGrants>
        <Total>0</Total>
      </ForeignGrants>
      <BenefitsToMembers>
        <Total>0</Total>
      </BenefitsToMembers>
      <CompCurrentOfficersDirectors>
        <Total>0</Total>
      </CompCurrentOfficersDirectors>
      <CompDisqualPersons>
        <Total>0</Total>
      </CompDisqualPersons>
      <OtherSalariesAndWages>
        <Total>130815</Total>
        <ProgramServices>130815</ProgramServices>
      </OtherSalariesAndWages>
      <PensionPlanContributions>
        <Total>0</Total>
      </PensionPlanContributions>
      <OtherEmployeeBenefits>
        <Total>40617</Total>
        <ProgramServices>40617</ProgramServices>
      </OtherEmployeeBenefits>
      <PayrollTaxes>
        <Total>10147</Total>
        <ProgramServices>10147</ProgramServices>
      </PayrollTaxes>
      <FeesForServicesManagement>
        <Total>0</Total>
      </FeesForServicesManagement>
      <FeesForServicesLegal>
        <Total>0</Total>
      </FeesForServicesLegal>
      <FeesForServicesAccounting>
        <Total>12470</Total>
        <ManagementAndGeneral>12470</ManagementAndGeneral>
      </FeesForServicesAccounting>
      <FeesForServicesLobbying>
        <Total>0</Total>
      </FeesForServicesLobbying>
      <FeesForServicesProfFundraising>
        <Total>0</Total>
      </FeesForServicesProfFundraising>
      <FeesForServicesInvstMgmntFees>
        <Total>0</Total>
      </FeesForServicesInvstMgmntFees>
      <FeesForServicesOther>
        <Total>0</Total>
      </FeesForServicesOther>
      <Advertising>
        <Total>1646</Total>
        <ProgramServices>1646</ProgramServices>
      </Advertising>
      <OfficeExpenses>
        <Total>24179</Total>
        <ProgramServices>24179</ProgramServices>
      </OfficeExpenses>
      <InformationTechnology>
        <Total>0</Total>
      </InformationTechnology>
      <Royalties>
        <Total>0</Total>
      </Royalties>
      <Occupancy>
        <Total>217131</Total>
        <ProgramServices>217131</ProgramServices>
      </Occupancy>
      <Travel>
        <Total>0</Total>
      </Travel>
      <TravelEntrtnmntPublicOfficials>
        <Total>0</Total>
      </TravelEntrtnmntPublicOfficials>
      <ConferencesMeetings>
        <Total>3663</Total>
        <ProgramServices>3663</ProgramServices>
      </ConferencesMeetings>
      <Interest>
        <Total>0</Total>
      </Interest>
      <PaymentsToAffiliates>
        <Total>0</Total>
      </PaymentsToAffiliates>
      <DepreciationDepletion>
        <Total>148588</Total>
        <ProgramServices>148588</ProgramServices>
      </DepreciationDepletion>
      <Insurance>
        <Total>1564</Total>
        <ProgramServices>1564</ProgramServices>
      </Insurance>
      <OtherExpenses>
        <Description>SERVICE CORDINATOR</Description>
        <Total>35236</Total>
        <ProgramServices>35236</ProgramServices>
      </OtherExpenses>
      <OtherExpenses>
        <Description>OTHER RENTING EXPENSES</Description>
        <Total>991</Total>
        <ProgramServices>991</ProgramServices>
      </OtherExpenses>
      <OtherExpenses>
        <Description>MISC. TAXES, LISCENSES, PERMIT</Description>
        <Total>1798</Total>
        <ProgramServices>1798</ProgramServices>
      </OtherExpenses>
      <OtherExpenses>
        <Description>MISC OPERATING</Description>
        <Total>63223</Total>
        <ProgramServices>63223</ProgramServices>
      </OtherExpenses>
      <OtherExpenses>
        <Description>MISC ADMIN EXPENSE</Description>
        <Total>4639</Total>
        <ProgramServices>4639</ProgramServices>
      </OtherExpenses>
      <AllOtherExpenses>
        <Total>0</Total>
      </AllOtherExpenses>
      <TotalFunctionalExpenses>
        <Total>696707</Total>
        <ProgramServices>684237</ProgramServices>
        <ManagementAndGeneral>12470</ManagementAndGeneral>
        <Fundraising>0</Fundraising>
      </TotalFunctionalExpenses>
      <CashNonInterestBearing>
        <BOY>44413</BOY>
        <EOY>43463</EOY>
      </CashNonInterestBearing>
      <SavingsAndTempCashInvestments>
        <EOY>0</EOY>
      </SavingsAndTempCashInvestments>
      <PledgesAndGrantsReceivable>
        <EOY>0</EOY>
      </PledgesAndGrantsReceivable>
      <AccountsReceivable>
        <BOY>349</BOY>
        <EOY>0</EOY>
      </AccountsReceivable>
      <ReceivablesFromOfficersEtc>
        <EOY>0</EOY>
      </ReceivablesFromOfficersEtc>
      <ReceivablesFromDisqualPersons>
        <EOY>0</EOY>
      </ReceivablesFromDisqualPersons>
      <OtherNotesLoansReceivableNet>
        <EOY>0</EOY>
      </OtherNotesLoansReceivableNet>
      <InventoriesForSaleOrUse>
        <EOY>0</EOY>
      </InventoriesForSaleOrUse>
      <PrepaidExpensesDeferredCharges>
        <BOY>7656</BOY>
        <EOY>4996</EOY>
      </PrepaidExpensesDeferredCharges>
      <LandBuildingsEquipmentBasis>3866005</LandBuildingsEquipmentBasis>
      <LandBldgEquipmentAccumDeprec>2398553</LandBldgEquipmentAccumDeprec>
      <LandBuildingsEquipmentBasisNet>
        <BOY>1469830</BOY>
        <EOY>1467452</EOY>
      </LandBuildingsEquipmentBasisNet>
      <InvestmentsPubTradedSecurities>
        <EOY>0</EOY>
      </InvestmentsPubTradedSecurities>
      <InvestmentsOtherSecurities>
        <EOY>0</EOY>
      </InvestmentsOtherSecurities>
      <InvestmentsProgramRelated>
        <EOY>0</EOY>
      </InvestmentsProgramRelated>
      <IntangibleAssets>
        <EOY>0</EOY>
      </IntangibleAssets>
      <OtherAssetsTotal>
        <BOY>830879</BOY>
        <EOY>741443</EOY>
      </OtherAssetsTotal>
      <TotalAssets>
        <BOY>2353127</BOY>
        <EOY>2257354</EOY>
      </TotalAssets>
      <AccountsPayableAccruedExpenses>
        <BOY>41461</BOY>
        <EOY>26447</EOY>
      </AccountsPayableAccruedExpenses>
      <DeferredRevenue>
        <EOY>214</EOY>
      </DeferredRevenue>
      <MortNotesPyblSecuredInvestProp>
        <BOY>2158808</BOY>
        <EOY>2141587</EOY>
      </MortNotesPyblSecuredInvestProp>
      <OtherLiabilities>
        <BOY>19627</BOY>
        <EOY>18996</EOY>
      </OtherLiabilities>
      <TotalLiabilities>
        <BOY>2219896</BOY>
        <EOY>2187244</EOY>
      </TotalLiabilities>
      <FollowSFAS117>X</FollowSFAS117>
      <UnrestrictedNetAssets>
        <BOY>133231</BOY>
        <EOY>70110</EOY>
      </UnrestrictedNetAssets>
      <TotalNetAssetsFundBalances>
        <BOY>133231</BOY>
        <EOY>70110</EOY>
      </TotalNetAssetsFundBalances>
      <TotalLiabNetAssetsFundBalances>
        <BOY>2353127</BOY>
        <EOY>2257354</EOY>
      </TotalLiabNetAssetsFundBalances>
      <ReconcilationRevenueExpenses>-63121</ReconcilationRevenueExpenses>
      <MethodOfAccountingAccrual>X</MethodOfAccountingAccrual>
      <AccountantCompileOrReview>false</AccountantCompileOrReview>
      <FSAudited>true</FSAudited>
      <AuditCommittee>true</AuditCommittee>
      <FinancialStatementSeparate>X</FinancialStatementSeparate>
      <FederalGrantAuditRequired>true</FederalGrantAuditRequired>
      <FederalGrantAuditPerformed>true</FederalGrantAuditPerformed>
    </IRS990>
    <IRS990ScheduleA documentId="IRS990ScheduleA" softwareId="10000105" softwareVersion="2010v3.2">
      <PubliclySupportedOrg509a2>X</PubliclySupportedOrg509a2>
      <GiftsGrantsContribReceived509>
        <Total>0</Total>
      </GiftsGrantsContribReceived509>
      <GrossReceiptsFromAdmissions>
        <CurrentTaxYearMinus4Years>557103</CurrentTaxYearMinus4Years>
        <CurrentTaxYearMinus3Years>579472</CurrentTaxYearMinus3Years>
        <CurrentTaxYearMinus2Years>596583</CurrentTaxYearMinus2Years>
        <CurrentTaxYearMinus1Year>631991</CurrentTaxYearMinus1Year>
        <CurrentTaxYear>596147</CurrentTaxYear>
        <Total>2961296</Total>
      </GrossReceiptsFromAdmissions>
      <GrossReceiptsFromNonUBI>
        <Total>0</Total>
      </GrossReceiptsFromNonUBI>
      <TaxRevLeviedForOrgBenefit509>
        <Total>0</Total>
      </TaxRevLeviedForOrgBenefit509>
      <ValueOfSvcsFcltsFurnishdByGovt>
        <Total>0</Total>
      </ValueOfSvcsFcltsFurnishdByGovt>
      <Total509>
        <CurrentTaxYearMinus4Years>557103</CurrentTaxYearMinus4Years>
        <CurrentTaxYearMinus3Years>579472</CurrentTaxYearMinus3Years>
        <CurrentTaxYearMinus2Years>596583</CurrentTaxYearMinus2Years>
        <CurrentTaxYearMinus1Year>631991</CurrentTaxYearMinus1Year>
        <CurrentTaxYear>596147</CurrentTaxYear>
        <Total>2961296</Total>
      </Total509>
      <AmtsRecdFromDisqualPersons>
        <Total>0</Total>
      </AmtsRecdFromDisqualPersons>
      <AmtsFromSubstContributors>
        <Total>0</Total>
      </AmtsFromSubstContributors>
      <PublicSupportTotal509>2961296</PublicSupportTotal509>
      <GrossInvestmentIncome509>
        <CurrentTaxYearMinus4Years>7035</CurrentTaxYearMinus4Years>
        <CurrentTaxYearMinus3Years>11563</CurrentTaxYearMinus3Years>
        <CurrentTaxYearMinus2Years>8174</CurrentTaxYearMinus2Years>
        <CurrentTaxYearMinus1Year>3610</CurrentTaxYearMinus1Year>
        <CurrentTaxYear>2203</CurrentTaxYear>
        <Total>32585</Total>
      </GrossInvestmentIncome509>
      <Post1975UBTI>
        <Total>0</Total>
      </Post1975UBTI>
      <InvestmentIncomeAndUBTI>
        <CurrentTaxYearMinus4Years>7035</CurrentTaxYearMinus4Years>
        <CurrentTaxYearMinus3Years>11563</CurrentTaxYearMinus3Years>
        <CurrentTaxYearMinus2Years>8174</CurrentTaxYearMinus2Years>
        <CurrentTaxYearMinus1Year>3610</CurrentTaxYearMinus1Year>
        <CurrentTaxYear>2203</CurrentTaxYear>
        <Total>32585</Total>
      </InvestmentIncomeAndUBTI>
      <NetIncomeFromOtherUBI>
        <Total>0</Total>
      </NetIncomeFromOtherUBI>
      <OtherIncome509>
        <Total>0</Total>
      </OtherIncome509>
      <TotalSupportTotal>
        <CurrentTaxYearMinus4Years>564138</CurrentTaxYearMinus4Years>
        <CurrentTaxYearMinus3Years>591035</CurrentTaxYearMinus3Years>
        <CurrentTaxYearMinus2Years>604757</CurrentTaxYearMinus2Years>
        <CurrentTaxYearMinus1Year>635601</CurrentTaxYearMinus1Year>
        <CurrentTaxYear>598350</CurrentTaxYear>
        <Total>2993881</Total>
      </TotalSupportTotal>
      <PublicSupportPercentage509>0.98910</PublicSupportPercentage509>
      <PriorYearSupportPercentage>0.98820</PriorYearSupportPercentage>
      <InvestmentIncomePercentage>0.01090</InvestmentIncomePercentage>
      <PriorYrInvestIncomePercentage>0.01180</PriorYrInvestIncomePercentage>
      <ThirtyThreePercntTestsCY509>X</ThirtyThreePercntTestsCY509>
    </IRS990ScheduleA>
    <IRS990ScheduleD documentId="IRS990ScheduleD" softwareId="10000105" softwareVersion="2010v3.2">
      <Land>
        <OtherCostOrOtherBasis>149947</OtherCostOrOtherBasis>
        <BookValue>149947</BookValue>
      </Land>
      <Buildings>
        <OtherCostOrOtherBasis>3239413</OtherCostOrOtherBasis>
        <Depreciation>2084005</Depreciation>
        <BookValue>1155408</BookValue>
      </Buildings>
      <Equipment>
        <OtherCostOrOtherBasis>50670</OtherCostOrOtherBasis>
        <Depreciation>49683</Depreciation>
        <BookValue>987</BookValue>
      </Equipment>
      <OtherLandBuildings>
        <OtherCostOrOtherBasis>425975</OtherCostOrOtherBasis>
        <Depreciation>264865</Depreciation>
        <BookValue>161110</BookValue>
      </OtherLandBuildings>
      <TotalOfBookValueLandBuildings>1467452</TotalOfBookValueLandBuildings>
      <OtherAssets>
        <Description>TENANTS' SECURITY DEPOSITS</Description>
        <BookValue>20012</BookValue>
      </OtherAssets>
      <OtherAssets>
        <Description>RESIDUAL RECEIPTS RESERVE</Description>
        <BookValue>69159</BookValue>
      </OtherAssets>
      <OtherAssets>
        <Description>REPLACEMENT RESERVE</Description>
        <BookValue>326224</BookValue>
      </OtherAssets>
      <OtherAssets>
        <Description>OTHER RESERVE</Description>
        <BookValue>162490</BookValue>
      </OtherAssets>
      <OtherAssets>
        <Description>ESCROW DEPOSITS</Description>
        <BookValue>80997</BookValue>
      </OtherAssets>
      <OtherAssets>
        <Description>DEFERRED FINANCING COSTS</Description>
        <BookValue>82561</BookValue>
      </OtherAssets>
      <TotalBookValueOtherAssets>741443</TotalBookValueOtherAssets>
      <OtherLiabilities>
        <Description>TENANTS' SECURITY DEPOSITS</Description>
        <Amount>18996</Amount>
      </OtherLiabilities>
      <TotalOfAmounts>18996</TotalOfAmounts>
      <TotalRevenue>633586</TotalRevenue>
      <TotalExpenses>696707</TotalExpenses>
      <ExcessOrDeficitForYear>-63121</ExcessOrDeficitForYear>
      <ExcessOrDeficitPerFS>-63121</ExcessOrDeficitPerFS>
      <TotRevenueEtcAuditedFinclStmt>633586</TotRevenueEtcAuditedFinclStmt>
      <RevenueSubtotal>633586</RevenueSubtotal>
      <TotalRevenuePerForm990>633586</TotalRevenuePerForm990>
      <TotExpensesEtcAuditedFinclStmt>696707</TotExpensesEtcAuditedFinclStmt>
      <ExpensesSubtotal>696707</ExpensesSubtotal>
      <TotalExpensesPerForm990>696707</TotalExpensesPerForm990>
    </IRS990ScheduleD>
    <IRS990ScheduleO documentId="IRS990ScheduleO" softwareId="10000105" softwareVersion="2010v3.2">
      <GeneralExplanation>
        <Identifier>Form 990-EZ, Part II, Line 26.1</Identifier>
        <ReturnReference>Total Liabilities.1</ReturnReference>
        <Explanation>TENANTS' SECURITY DEPOSITS - Beginning $19627 TENANTS' SECURITY DEPOSITS - Ending $18996</Explanation>
      </GeneralExplanation>
      <GeneralExplanation>
        <Identifier>Form 990-EZ, Part II, Line 26.1007</Identifier>
        <ReturnReference>Total Liabilities.1007</ReturnReference>
        <Explanation>Secured Mortgages and Notes Payable - Beginning $2158808 Secured Mortgages and Notes Payable - Ending $2141587</Explanation>
      </GeneralExplanation>
      <GeneralExplanation>
        <Identifier>Form 990-EZ, Part II, Line 26.1003</Identifier>
        <ReturnReference>Total Liabilities.1003</ReturnReference>
        <Explanation>Deferred Revenue - Beginning $0 Deferred Revenue - Ending $214</Explanation>
      </GeneralExplanation>
      <GeneralExplanation>
        <Identifier>Form 990-EZ, Part II, Line 26.1001</Identifier>
        <ReturnReference>Total Liabilities.1001</ReturnReference>
        <Explanation>Accounts Payable and Accrued Expenses - Beginning $41461 Accounts Payable and Accrued Expenses - Ending $26447</Explanation>
      </GeneralExplanation>
      <GeneralExplanation>
        <Identifier>Form 990-EZ, Part II, Line 24.8</Identifier>
        <ReturnReference>Other Assets.8</ReturnReference>
        <Explanation>OTHER RESERVE - Beginning $551506 OTHER RESERVE - Ending $162490</Explanation>
      </GeneralExplanation>
      <GeneralExplanation>
        <Identifier>Form 990-EZ, Part II, Line 24.7</Identifier>
        <ReturnReference>Other Assets.7</ReturnReference>
        <Explanation>DEFERRED FINANCING COSTS - Beginning $85056 DEFERRED FINANCING COSTS - Ending $82561</Explanation>
      </GeneralExplanation>
      <GeneralExplanation>
        <Identifier>Form 990-EZ, Part II, Line 24.6</Identifier>
        <ReturnReference>Other Assets.6</ReturnReference>
        <Explanation>ESCROW DEPOSITS - Beginning $81270 ESCROW DEPOSITS - Ending $80997</Explanation>
      </GeneralExplanation>
      <GeneralExplanation>
        <Identifier>Form 990-EZ, Part II, Line 24.4</Identifier>
        <ReturnReference>Other Assets.4</ReturnReference>
        <Explanation>RESIDUAL RECEIPTS RESERVE - Beginning $54909 RESIDUAL RECEIPTS RESERVE - Ending $69159</Explanation>
      </GeneralExplanation>
      <GeneralExplanation>
        <Identifier>Form 990-EZ, Part II, Line 24.3</Identifier>
        <ReturnReference>Other Assets.3</ReturnReference>
        <Explanation>REPLACEMENT RESERVE - Beginning $37516 REPLACEMENT RESERVE - Ending $326224</Explanation>
      </GeneralExplanation>
      <GeneralExplanation>
        <Identifier>Form 990-EZ, Part II, Line 24.1</Identifier>
        <ReturnReference>Other Assets.1</ReturnReference>
        <Explanation>TENANTS' SECURITY DEPOSITS - Beginning $20622 TENANTS' SECURITY DEPOSITS - Ending $20012</Explanation>
      </GeneralExplanation>
      <GeneralExplanation>
        <Identifier>Form 990-EZ, Part II, Line 24.1011</Identifier>
        <ReturnReference>Other Assets.1011</ReturnReference>
        <Explanation>Prepaid Expenses and Deferred Charges - Beginning $7656 Prepaid Expenses and Deferred Charges - Ending $4996</Explanation>
      </GeneralExplanation>
      <GeneralExplanation>
        <Identifier>Form 990-EZ, Part II, Line 24.1005</Identifier>
        <ReturnReference>Other Assets.1005</ReturnReference>
        <Explanation>Accounts Receivable - Beginning $349 Accounts Receivable - Ending $0</Explanation>
      </GeneralExplanation>
      <GeneralExplanation>
        <Identifier>Form 990-EZ, Part II, Line 24.1004</Identifier>
        <ReturnReference>Other Assets.1004</ReturnReference>
        <Explanation>Miscellaneous - Beginning $20362 Miscellaneous - Ending $41326</Explanation>
      </GeneralExplanation>
      <GeneralExplanation>
        <Identifier>Form 990-EZ, Part II, Line 24.1003</Identifier>
        <ReturnReference>Other Assets.1003</ReturnReference>
        <Explanation>Machinery and Equipment - Beginning $1382 Machinery and Equipment - Ending $987</Explanation>
      </GeneralExplanation>
      <GeneralExplanation>
        <Identifier>Form 990-EZ, Part II, Line 24.1002</Identifier>
        <ReturnReference>Other Assets.1002</ReturnReference>
        <Explanation>Furniture and Fixtures - Beginning $96167 Furniture and Fixtures - Ending $119784</Explanation>
      </GeneralExplanation>
      <GeneralExplanation>
        <Identifier>Form 990-EZ, Part I, Line 16.5</Identifier>
        <ReturnReference>Other Expenses.5</ReturnReference>
        <Explanation>OTHER RENTING EXPENSES $991</Explanation>
      </GeneralExplanation>
      <GeneralExplanation>
        <Identifier>Form 990-EZ, Part I, Line 16.4</Identifier>
        <ReturnReference>Other Expenses.4</ReturnReference>
        <Explanation>MISC. TAXES, LISCENSES, PERMIT $1798</Explanation>
      </GeneralExplanation>
      <GeneralExplanation>
        <Identifier>Form 990-EZ, Part I, Line 16.3</Identifier>
        <ReturnReference>Other Expenses.3</ReturnReference>
        <Explanation>MISC ADMIN EXPENSE $4639</Explanation>
      </GeneralExplanation>
      <GeneralExplanation>
        <Identifier>Form 990-EZ, Part I, Line 16.2</Identifier>
        <ReturnReference>Other Expenses.2</ReturnReference>
        <Explanation>SERVICE CORDINATOR $35236</Explanation>
      </GeneralExplanation>
      <GeneralExplanation>
        <Identifier>Form 990-EZ, Part I, Line 16.1</Identifier>
        <ReturnReference>Other Expenses.1</ReturnReference>
        <Explanation>MISC OPERATING $63223</Explanation>
      </GeneralExplanation>
      <GeneralExplanation>
        <Identifier>Form 990-EZ, Part I, Line 16.1012</Identifier>
        <ReturnReference>Other Expenses.1012</ReturnReference>
        <Explanation>Insurance $1564</Explanation>
      </GeneralExplanation>
      <GeneralExplanation>
        <Identifier>Form 990-EZ, Part I, Line 16.1010</Identifier>
        <ReturnReference>Other Expenses.1010</ReturnReference>
        <Explanation>Amortization $2496</Explanation>
      </GeneralExplanation>
      <GeneralExplanation>
        <Identifier>Form 990-EZ, Part I, Line 16.1009</Identifier>
        <ReturnReference>Other Expenses.1009</ReturnReference>
        <Explanation>Depreciation $146092</Explanation>
      </GeneralExplanation>
      <GeneralExplanation>
        <Identifier>Form 990-EZ, Part I, Line 16.1007</Identifier>
        <ReturnReference>Other Expenses.1007</ReturnReference>
        <Explanation>Conferences, Conventions, and Meetings $3663</Explanation>
      </GeneralExplanation>
      <GeneralExplanation>
        <Identifier>Form 990-EZ, Part I, Line 16.1002</Identifier>
        <ReturnReference>Other Expenses.1002</ReturnReference>
        <Explanation>Office Expenses $24179</Explanation>
      </GeneralExplanation>
      <GeneralExplanation>
        <Identifier>Form 990-EZ, Part I, Line 16.1001</Identifier>
        <ReturnReference>Other Expenses.1001</ReturnReference>
        <Explanation>Advertising and Promotion $1646</Explanation>
      </GeneralExplanation>
      <GeneralExplanation>
        <Identifier>Form 990, Part VI, Line 19</Identifier>
        <ReturnReference>Form 990, Part VI, Line 19: Other Organization Documents Publicly Available</ReturnReference>
        <Explanation>UPON REQUEST.</Explanation>
      </GeneralExplanation>
      <GeneralExplanation>
        <Identifier>Form 990, Part VI, Line 11</Identifier>
        <ReturnReference>Form 990, Part VI, Line 11: Form 990 Review Process</ReturnReference>
        <Explanation>No review was or will be conducted.</Explanation>
      </GeneralExplanation>
    </IRS990ScheduleO>
  </ReturnData>
</Return>